Workbook
Name FirstYear: Inputs!$D$9
Name GuideHigh: Inputs!$E$68
Name GuideLow: Inputs!$D$68
Name LastActual: Inputs!$D$10
Name ModelChecks: Cover!$G$29
Name Scenario: Outputs!$D$5
Name ScenarioList: Inputs!$D$131:$D$133
Name ScenarioName: Inputs!$D$135
Name SharesOut: Inputs!$D$15
Name TaxRate: Inputs!$D$12
Name TGR: Outputs!$D$9
Name ValDate: Inputs!$D$11
Name WACC: Outputs!$D$8

Sheet Cover
B1: Kofola ČeskoSlovensko a.s.
B3: 3-statement model, DCF and comparables | E3: Scenario
B4: Prepared by Matúš Balko | Valuation date 30.06.2026 | CZK m unless stated
B6: Contents
B7: Dashboard | C7: One-page summary: company overview, valuation and key charts
B8: Outputs | C8: Scenario switch, DCF summary, football field, scenario and sensitivity tables
B9: Inputs | C9: General inputs, scenario drivers, WACC build
B10: Model | C10: Schedules, three statements, FCF bridge, DCF
B11: Comps | C11: Trading comparables and precedent transactions
B12: Hist | C12: Source data from the annual and interim reports
B14: Conventions
B15: Hardcoded input or source figure | C15: 1,234.5
B16: Formula, including links to other sheets | C16: 1,234.5
B17: Scenario: pick Base / Upside / Downside case in the drop-down on Cover, Outputs or Inputs
B18: Costs and cash outflows are negative, subtotals are plain sums
B19: A = actual, F = forecast, fiscal year = calendar year
B20: Check rows are rounded to 0.1 (source figures are to the nearest CZK thousand)
B22: Model checks
B23: Check | F23: Difference | G23: Status
B24: EBITDA vs reported | F24: =SUMPRODUCT(ABS(Model!D39:L39)) -> 0 | G24: =IFERROR(IF(F24=0,"OK","ERROR"),"ERROR") -> OK
B25: Net profit vs reported | F25: =SUMPRODUCT(ABS(Model!D71:L71)) -> 0 | G25: =IFERROR(IF(F25=0,"OK","ERROR"),"ERROR") -> OK
B26: Balance sheet balances | F26: =SUMPRODUCT(ABS(Model!D106:L106)) -> 0 | G26: =IFERROR(IF(F26=0,"OK","ERROR"),"ERROR") -> OK
B27: Closing cash vs balance sheet | F27: =SUMPRODUCT(ABS(Model!D144:L144)) -> 0 | G27: =IFERROR(IF(F27=0,"OK","ERROR"),"ERROR") -> OK
B28: DCF: sum of discounted cash flows vs XNPV (both methods) | F28: =ROUND(ABS(Model!D286-Model!D287)+ABS(Model!D325-Model!D326),1) -> 0 | G28: =IFERROR(IF(F28=0,"OK","ERROR"),"ERROR") -> OK
B29: All checks | G29: =IF(COUNTIF(G24:G28,"OK")=ROWS(G24:G28),"OK","ERROR") -> OK

Sheet Dashboard
B1: Kofola ČeskoSlovensko | Dashboard
B2: ="CZK m unless stated | Valuation date 30.06.2026 | Active scenario: "&ScenarioName -> CZK m unless stated | Valuation date 30.06.2026 | Active scenario: Base case
B4: Company overview | P4: Data: company overview
B6: Kofola ČeskoSlovensko a.s. (PSE: KOFOL) | F6: ="Share price at 30.06.2026: CZK "&FIXED(Q9,0) -> Share price at 30.06.2026: CZK 493 | N6: ="Market capitalisation: CZK "&SUBSTITUTE(FIXED(Q11/1000,1,TRUE),",",".")&"bn" -> Market capitalisation: CZK 10.5bn | P6: Company | Q6: Kofola ČeskoSlovensko a.s.
P7: Ticker | Q7: KOFOL (Prague Stock Exchange)
B8: Central European producer of soft drinks, mineral waters, syrups, fresh juices and teas. Beer since the Pivovary Zubr deal closed in March 2024. | P8: Valuation date | Q8: =ValDate -> 46203
B9: Own brands include Kofola, Vinea, Rajec, Radenska, Studenac, Jupí, Semtex, UGO and Leros, plus the beers Zubr, Holba and Litovel. | P9: Share price at 30.06.2026 (CZK) | Q9: =Inputs!D113 -> 493
B10: Fourteen plants in the Czech Republic, Slovakia, Slovenia, Croatia and Poland, selling through retail, HoReCa and impulse channels. | P10: Shares outstanding (m) | Q10: =SharesOut -> 21.333731
B11: Four reporting segments: CzechoSlovakia, Adriatic, Fresh & Herbs, and Beers & Ciders. | P11: Market capitalisation (CZK m) | Q11: =Inputs!D114 -> 10517.529
B12: ="FY2025A revenue CZK "&SUBSTITUTE(FIXED(Model!G16/1000,1,TRUE),",",".")&"bn, adjusted EBITDA CZK "&SUBSTITUTE(FIXED(Model!G38/1000,1,TRUE),",",".")&"bn ("&SUBSTITUTE(FIXED(Model!G48*100,1,TRUE),",",".")&"% margin), net debt / adjusted EBITDA "&SUBSTITUTE(FIXED(Model!G221,1,TRUE),",",".")&"x, dividend CZK "&FIXED(Model!G77,0)&" per share." -> FY2025A revenue CZK 10.8bn, adjusted EBITDA CZK 1.8bn (16.9% margin), net debt / adjusted EBITDA 3.0x, dividend CZK 21 per share. | P12: Net debt at 30.06.2026 (CZK m) | Q12: =Inputs!D115 -> 6441.73
B13: ="2026 EBITDA guidance of CZK "&SUBSTITUTE(FIXED(GuideLow/1000,1,TRUE),",",".")&" to "&SUBSTITUTE(FIXED(GuideHigh/1000,1,TRUE),",",".")&"bn. Acquisitions in H1 2026: Nobilis Tilia (natural cosmetics) and Alta Fermentación (Latin America)." -> 2026 EBITDA guidance of CZK 1.8 to 1.9bn. Acquisitions in H1 2026: Nobilis Tilia (natural cosmetics) and Alta Fermentación (Latin America). | P13: EV / LTM adjusted EBITDA, bonus-normalised (x) | Q13: =Comps!G38 -> 9.787734
B14: ="DCF value per share CZK "&FIXED(Q15,0)&" (perpetuity growth) and CZK "&FIXED(Q16,0)&" (exit multiple), against a share price of CZK "&FIXED(Q9,0)&" at 30.06.2026." -> DCF value per share CZK 416 (perpetuity growth) and CZK 512 (exit multiple), against a share price of CZK 493 at 30.06.2026. | P14: P / E on LTM adjusted net profit, bonus-normalised (x) | Q14: =Comps!H38 -> 22.807018
B15: After 30.06.2026, not in the valuation: 52% of COKAFE (August) and the Bohemia Healing Marienbad Waters business for CZK 414m (September). | P15: DCF value per share, perpetuity growth (CZK) | Q15: =Outputs!D26 -> 415.70732
B16: Also signed in September 2026: 51% of Chachar catering (Ostrava-based chain of 43 pubs, closing by the end of 2026). | P16: DCF value per share, exit multiple (CZK) | Q16: =Outputs!E26 -> 511.87859
B17: Share price, last 52 weeks (CZK) | I17: Football field (CZK per share) | P17: Average of base values, football field (CZK) | Q17: =Outputs!G46 -> 459.72115
P19: Data: football field (CZK per share)
P20: Method | Q20: Low | R20: High | S20: Base
P21: =Outputs!B40 -> DCF (perpetuity growth) | Q21: =Outputs!D40 -> 292.45327 | R21: =Outputs!F40 -> 607.77376 | S21: =Outputs!G40 -> 415.70732
P22: =Outputs!B41 -> DCF (exit multiple) | Q22: =Outputs!D41 -> 420.92545 | R22: =Outputs!F41 -> 606.47851 | S22: =Outputs!G41 -> 511.87859
P23: =Outputs!B42 -> Trading comps (EV / EBITDA) | Q23: =Outputs!D42 -> 200.30553 | R23: =Outputs!F42 -> 632.2358 | S23: =Outputs!G42 -> 451.57755
P24: =Outputs!B43 -> Trading comps (P / E) | Q24: =Outputs!D43 -> 216.70021 | R24: =Outputs!F43 -> 421.90739 | S24: =Outputs!G43 -> 292.33561
P25: =Outputs!B44 -> Precedent transactions (EV / EBITDA) | Q25: =Outputs!D44 -> 577.18758 | R25: =Outputs!F44 -> 985.89619 | S25: =Outputs!G44 -> 740.66789
P26: =Outputs!B45 -> 52-week trading range | Q26: =Outputs!D45 -> 450 | R26: =Outputs!F45 -> 546 | S26: =Outputs!G45 -> 493
P27: ="Average of base values (CZK "&FIXED(S27,0)&")" -> Average of base values (CZK 460) | S27: =Outputs!G46 -> 459.72115
P29: Data: financials
P30: CZK m unless stated | Q30: =Model!D$4&Model!D$6 -> 2022A | R30: =Model!E$4&Model!E$6 -> 2023A | S30: =Model!F$4&Model!F$6 -> 2024A | T30: =Model!G$4&Model!G$6 -> 2025A | U30: =Model!H$4&Model!H$6 -> 2026F | V30: =Model!I$4&Model!I$6 -> 2027F | W30: =Model!J$4&Model!J$6 -> 2028F | X30: =Model!K$4&Model!K$6 -> 2029F | Y30: =Model!L$4&Model!L$6 -> 2030F
P31: Revenue growth | R31: =Model!E24 -> 0.10346535 | S31: =Model!F24 -> 0.27523839 | T31: =Model!G24 -> -0.029563832 | U31: =Model!H24 -> 0.069292779 | V31: =Model!I24 -> 0.044027053 | W31: =Model!J24 -> 0.03921314 | X31: =Model!K24 -> 0.034998888 | Y31: =Model!L24 -> 0.032953725
P32: Adjusted EBITDA margin | Q32: =Model!D48 -> 0.14100203 | R32: =Model!E48 -> 0.1442335 | S32: =Model!F48 -> 0.16702769 | T32: =Model!G48 -> 0.16890344 | U32: =Model!H48 -> 0.164 | V32: =Model!I48 -> 0.161 | W32: =Model!J48 -> 0.162 | X32: =Model!K48 -> 0.163 | Y32: =Model!L48 -> 0.163
P34: CzechoSlovakia | Q34: =Model!D11 -> 5735.854 | R34: =Model!E11 -> 6314.707 | S34: =Model!F11 -> 7015.597 | T34: =Model!G11 -> 6542.522 | U34: =Model!H11 -> 7196.7742 | V34: =Model!I11 -> 7484.6452 | W34: =Model!J11 -> 7746.6077 | X34: =Model!K11 -> 7979.006 | Y34: =Model!L11 -> 8218.3762
B35: Revenue by segment (CZK m) and revenue growth | I35: Adjusted EBITDA, free cash flow and dividends (CZK m) | P35: Adriatic | Q35: =Model!D12 -> 1413.483 | R35: =Model!E12 -> 1514.892 | S35: =Model!F12 -> 1683.172 | T35: =Model!G12 -> 1652.173 | U35: =Model!H12 -> 1685.2165 | V35: =Model!I12 -> 1735.773 | W35: =Model!J12 -> 1787.8461 | X35: =Model!K12 -> 1841.4815 | Y35: =Model!L12 -> 1887.5186
P36: Fresh & Herbs | Q36: =Model!D13 -> 876.848 | R36: =Model!E13 -> 1026.918 | S36: =Model!F13 -> 1230.533 | T36: =Model!G13 -> 1420.817 | U36: =Model!H13 -> 1676.5641 | V36: =Model!I13 -> 1844.2205 | W36: =Model!J13 -> 1991.7581 | X36: =Model!K13 -> 2131.1812 | Y36: =Model!L13 -> 2259.052
P37: Beers & Ciders | Q37: =Model!D14 -> 0 | R37: =Model!E14 -> 0 | S37: =Model!F14 -> 1400.375 | T37: =Model!G14 -> 1479.289 | U37: =Model!H14 -> 1420.1174 | V37: =Model!I14 -> 1441.4192 | W37: =Model!J14 -> 1470.2476 | X37: =Model!K14 -> 1499.6525 | Y37: =Model!L14 -> 1529.6456
P38: Consolidation adjustments | Q38: =Model!D15 -> -150.901 | R38: =Model!E15 -> -166.414 | S38: =Model!F15 -> -247.724 | T38: =Model!G15 -> -340.473 | U38: =Model!H15 -> -479.14689 | V38: =Model!I15 -> -500.24231 | W38: =Model!J15 -> -519.85838 | X38: =Model!K15 -> -538.05285 | Y38: =Model!L15 -> -555.78369
P39: Revenue | Q39: =Model!D16 -> 7875.284 | R39: =Model!E16 -> 8690.103 | S39: =Model!F16 -> 11081.953 | T39: =Model!G16 -> 10754.328 | U39: =Model!H16 -> 11499.525 | V39: =Model!I16 -> 12005.815 | W39: =Model!J16 -> 12476.601 | X39: =Model!K16 -> 12913.268 | Y39: =Model!L16 -> 13338.809
P41: Adjusted EBITDA | Q41: =Model!D38 -> 1110.431 | R41: =Model!E38 -> 1253.404 | S41: =Model!F38 -> 1850.993 | T41: =Model!G38 -> 1816.443 | U41: =Model!H38 -> 1885.9221 | V41: =Model!I38 -> 1932.9363 | W41: =Model!J38 -> 2021.2094 | X41: =Model!K38 -> 2104.8627 | Y41: =Model!L38 -> 2174.2258
P42: Free cash flow | Q42: =Model!D155 -> 189.956 | R42: =Model!E155 -> 697.247 | S42: =Model!F155 -> 452.59 | T42: =Model!G155 -> -374.658 | U42: =Model!H155 -> -20.694986 | V42: =Model!I155 -> 137.09579 | W42: =Model!J155 -> 280.45396 | X42: =Model!K155 -> 375.26213 | Y42: =Model!L155 -> 462.03048
P43: Dividends paid to owners | Q43: =-Model!D135 -> 253.012 | R43: =-Model!E135 -> 286.601 | S43: =-Model!F135 -> 449.83 | T43: =-Model!G135 -> 274.84 | U43: =-Model!H135 -> 447.16405 | V43: =-Model!I135 -> 448.00835 | W43: =-Model!J135 -> 448.00835 | X43: =-Model!K135 -> 448.00835 | Y43: =-Model!L135 -> 448.00835
P44: Net profit attributable to owners | Q44: =Model!D70 -> 269.15 | R44: =Model!E70 -> 365.397 | S44: =Model!F70 -> 597.891 | T44: =Model!G70 -> 673.923 | U44: =Model!H70 -> 456.24891 | V44: =Model!I70 -> 375.81229 | W44: =Model!J70 -> 397.53971 | X44: =Model!K70 -> 434.45686 | Y44: =Model!L70 -> 469.71165
P45: Net debt / adjusted EBITDA (x) | Q45: =Model!D221 -> 2.9673523 | R45: =Model!E221 -> 2.2815501 | S45: =Model!F221 -> 2.1359735 | T45: =Model!G221 -> 3.0198355 | U45: =Model!H221 -> 3.5315344 | V45: =Model!I221 -> 3.59621 | W45: =Model!J221 -> 3.5204172 | X45: =Model!K221 -> 3.4182127 | Y45: =Model!L221 -> 3.3085778
P47: Data: scenarios
P48: Net debt / adjusted EBITDA (x) | Q48: =Q$30 -> 2022A | R48: =R$30 -> 2023A | S48: =S$30 -> 2024A | T48: =T$30 -> 2025A | U48: =U$30 -> 2026F | V48: =V$30 -> 2027F | W48: =W$30 -> 2028F | X48: =X$30 -> 2029F | Y48: =Y$30 -> 2030F
P49: Actual | Q49: =Q45 -> 2.9673523 | R49: =R45 -> 2.2815501 | S49: =S45 -> 2.1359735 | T49: =T45 -> 3.0198355
P50: =Inputs!D131 -> Base case | T50: =T$45 -> 3.0198355 | U50: =Outputs!H84 -> 3.5315344 | V50: =Outputs!I84 -> 3.59621 | W50: =Outputs!J84 -> 3.5204172 | X50: =Outputs!K84 -> 3.4182127 | Y50: =Outputs!L84 -> 3.3085778
P51: =Inputs!D132 -> Upside case | T51: =T$45 -> 3.0198355 | U51: =Outputs!H85 -> 3.267601 | V51: =Outputs!I85 -> 3.084125 | W51: =Outputs!J85 -> 2.8729433 | X51: =Outputs!K85 -> 2.6455305 | Y51: =Outputs!L85 -> 2.4459359
P52: =Inputs!D133 -> Downside case | T52: =T$45 -> 3.0198355 | U52: =Outputs!H86 -> 4.1700339 | V52: =Outputs!I86 -> 4.2527124 | W52: =Outputs!J86 -> 4.4832942 | X52: =Outputs!K86 -> 4.3864068 | Y52: =Outputs!L86 -> 4.3019082
B53: Net debt / adjusted EBITDA by scenario (x) | I53: DCF value per share by scenario (CZK)
P54: DCF value per share (CZK) | Q54: =Inputs!D131 -> Base case | R54: =Inputs!D132 -> Upside case | S54: =Inputs!D133 -> Downside case
P55: DCF (perpetuity growth) | Q55: =Outputs!D56 -> 415.70732 | R55: =Outputs!D57 -> 633.04507 | S55: =Outputs!D58 -> 179.98892
P56: DCF (exit multiple) | Q56: =Outputs!E56 -> 511.87859 | R56: =Outputs!E57 -> 653.9609 | S56: =Outputs!E58 -> 309.91993
P57: Share price at 30.06.2026 | Q57: =$Q$9 -> 493 | R57: =$Q$9 -> 493 | S57: =$Q$9 -> 493
P59: Data: share price (CZK)
P60: Prague Stock Exchange daily closing prices, 01.07.2025 to 30.06.2026 (Yahoo Finance)
P61: Date | Q61: Close
P62: 45839 | Q62: 536
P63: 45840 | Q63: 536
P64: 45841 | Q64: 534
P65: 45842 | Q65: 541
P66: 45845 | Q66: 546
P67: 45846 | Q67: 540
P68: 45847 | Q68: 546
P69: 45848 | Q69: 544
P70: 45849 | Q70: 541
B71: Sources: Kofola annual report 2025 and H1 2026 interim report, Prague Stock Exchange closing prices (Yahoo Finance), model outputs for the active scenario. | P71: 45852 | Q71: 538
B72: Free cash flow is cash flow from operations after interest, less capex and lease principal, plus disposal proceeds and interest received. | P72: 45853 | Q72: 540
B73: The dashed line in the football field is the average of the two DCF base values and the EV / EBITDA comps median. P / E and transactions are cross-checks only. | P73: 45854 | Q73: 533
P74: 45855 | Q74: 530
P75: 45856 | Q75: 510
P76: 45859 | Q76: 518
P77: 45860 | Q77: 522
P78: 45861 | Q78: 524
P79: 45862 | Q79: 526
P80: 45863 | Q80: 531
P81: 45866 | Q81: 526
P82: 45867 | Q82: 526
P83: 45868 | Q83: 522
P84: 45869 | Q84: 520
P85: 45870 | Q85: 516
... P311: 46203 | Q311: 493

Sheet Outputs
B1: Kofola ČeskoSlovensko | Outputs
B2: CZK m unless stated
B4: Scenario
B5: Active scenario | D5: 1
B7: DCF inputs
B8: WACC | D8: =Inputs!D123 -> 0.065735342
B9: Terminal growth rate | D9: 0.02 | N9: CNB inflation target
B10: Exit multiple (EV / EBITDA) | D10: =Comps!G30 -> 9.2896732
B12: DCF summary
D15: Perpetuity | E15: Exit
B16: CZK m unless stated | D16: growth | E16: multiple
B17: PV of discrete forecast (H2 2026F to 2030F) | C17: CZK m | D17: =Model!L286 -> 2609.0505 | E17: =Model!L325 -> 2609.0505
B18: PV of terminal value | C18: CZK m | D18: =Model!L287 -> 13108.111 | E18: =Model!L326 -> 15159.803
B19: Enterprise value | C19: CZK m | D19: =SUM(D17:D18) -> 15717.161 | E19: =SUM(E17:E18) -> 17768.853
B20: Less: net debt at 30.06.2026 | C20: CZK m | D20: =Model!D292 -> -6441.73 | E20: =Model!D331 -> -6441.73
B21: Less: non-controlling interests | C21: CZK m | D21: =Model!D293 -> -350.207 | E21: =Model!D332 -> -350.207
B22: Plus: equity-accounted investments | C22: CZK m | D22: =Model!D294 -> 390.528 | E22: =Model!D333 -> 390.528
B23: Less: FY2025 dividend unpaid at 30.06.2026 | C23: CZK m | D23: =Model!D295 -> -447.16405 | E23: =Model!D334 -> -447.16405
B24: Equity value | C24: CZK m | D24: =SUM(D19:D23) -> 8868.5881 | E24: =SUM(E19:E23) -> 10920.28
B25: Shares outstanding | C25: m | D25: =SharesOut -> 21.333731 | E25: =SharesOut -> 21.333731
B26: Equity value per share | C26: CZK | D26: =D24/D25 -> 415.70732 | E26: =E24/E25 -> 511.87859
B27: Share price at 30.06.2026 | C27: CZK | D27: =Model!L294 -> 493 | E27: =Model!L333 -> 493
B28: Upside / (downside) | C28: % | D28: =D26/D27-1 -> -0.15678028 | E28: =E26/E27-1 -> 0.03829328
B30: Cross-checks
B31: Terminal value as % of enterprise value | C31: % | D31: =Model!K287 -> 0.83399989 | E31: =Model!K326 -> 0.8531672
B32: Implied EV / 2030F EBITDA | C32: x | D32: =Model!L296 -> 7.7800865 | E32: =D10 -> 9.2896732
B33: Implied perpetuity growth rate | C33: % | D33: =D9 -> 0.02 | E33: =Model!L335 -> 0.025958693
B35: Football field
G38: Base /
B39: Value per share | D39: Low | E39: Range | F39: High | G39: median
B40: DCF (perpetuity growth) | C40: CZK | D40: =MIN(F117:H119) -> 292.45327 | E40: =F40-D40 -> 315.32049 | F40: =MAX(F117:H119) -> 607.77376 | G40: =G118 -> 415.70732
B41: DCF (exit multiple) | C41: CZK | D41: =MIN(F142:H144) -> 420.92545 | E41: =F41-D41 -> 185.55306 | F41: =MAX(F142:H144) -> 606.47851 | G41: =G143 -> 511.87859
B42: Trading comps (EV / EBITDA) | C42: CZK | D42: =Comps!D67 -> 200.30553 | E42: =Comps!E67 -> 431.93028 | F42: =Comps!F67 -> 632.2358 | G42: =Comps!G67 -> 451.57755
B43: Trading comps (P / E) | C43: CZK | D43: =Comps!D68 -> 216.70021 | E43: =Comps!E68 -> 205.20718 | F43: =Comps!F68 -> 421.90739 | G43: =Comps!G68 -> 292.33561
B44: Precedent transactions (EV / EBITDA) | C44: CZK | D44: =Comps!D69 -> 577.18758 | E44: =Comps!E69 -> 408.70861 | F44: =Comps!F69 -> 985.89619 | G44: =Comps!G69 -> 740.66789
B45: 52-week trading range | C45: CZK | D45: =MIN(Dashboard!$Q$62:$Q$311) -> 450 | E45: =F45-D45 -> 96 | F45: =MAX(Dashboard!$Q$62:$Q$311) -> 546 | G45: =Inputs!D113 -> 493 | N45: PSE closing prices 01.07.2025 to 30.06.2026 (Yahoo Finance)
B46: Average of base values (DCF and EV / EBITDA comps) | C46: CZK | G46: =AVERAGE(G40:G42) -> 459.72115
B48: Scenario analysis
B51: Valuation and key metrics
D52: Perpetuity | E52: Exit mult. | F52: Perpetuity | G52: Exit mult. | H52: Adj. EBITDA | I52: Adj. EBITDA | J52: EPS | K52: FCF after | L52: ND / EBITDA
B53: Scenario | C53: Case | D53: DCF | E53: DCF | F53: upside | G53: upside | H53: 2026F | I53: 2030F | J53: 2026F | K53: div. 26-30F | L53: 2028F
D54: CZK | E54: CZK | F54: % | G54: % | H54: CZK m | I54: CZK m | J54: CZK | K54: CZK m | L54: x
B55: Live: active case | D55: =Model!L293 -> 415.70732 | E55: =Model!L332 -> 511.87859 | F55: =Model!L295 -> -0.15678028 | G55: =Model!L334 -> 0.03829328 | H55: =Model!H38 -> 1885.9221 | I55: =Model!L38 -> 2174.2258 | J55: =Model!H76 -> 21.386269 | K55: =SUM(Model!H157:L157) -> -1005.0501 | L55: =Model!J221 -> 3.5204172
B56: =Inputs!D131 -> Base case | C56: 1 | D56: 415.70732 | E56: 511.87859 | F56: -0.15678028 | G56: 0.03829328 | H56: 1885.9221 | I56: 2174.2258 | J56: 21.386269 | K56: -1005.0501 | L56: 3.5204172
B57: =Inputs!D132 -> Upside case | C57: 2 | D57: 633.04507 | E57: 653.9609 | F57: 0.28406707 | G57: 0.32649269 | H57: 2006.154 | I57: 2476.2881 | J57: 25.34821 | K57: 164.46712 | L57: 2.8729433
B58: =Inputs!D133 -> Downside case | C58: 3 | D58: 179.98892 | E58: 309.91993 | F58: -0.63491091 | G58: -0.37135916 | H58: 1621.4213 | I58: 1671.4049 | J58: 12.670303 | K58: -1068.8705 | L58: 4.4832942
B60: Forecast by scenario
B61: CZK m unless stated | G61: Case | H61: =Model!H$4 -> 2026 | I61: =Model!I$4 -> 2027 | J61: =Model!J$4 -> 2028 | K61: =Model!K$4 -> 2029 | L61: =Model!L$4 -> 2030
B63: Revenue | C63: CZK m | H63: =Model!H16 -> 11499.525 | I63: =Model!I16 -> 12005.815 | J63: =Model!J16 -> 12476.601 | K63: =Model!K16 -> 12913.268 | L63: =Model!L16 -> 13338.809
B64: =Inputs!D131 -> Base case | G64: 1 | H64: 11499.525 | I64: 12005.815 | J64: 12476.601 | K64: 12913.268 | L64: 13338.809
B65: =Inputs!D132 -> Upside case | G65: 2 | H65: 11731.895 | I65: 12407.364 | J65: 13039.078 | K65: 13619.736 | L65: 14150.217
B66: =Inputs!D133 -> Downside case | G66: 3 | H66: 11182.216 | I66: 11412.576 | J66: 11099.714 | K66: 11450.953 | L66: 11688.146
B68: Adjusted EBITDA | C68: CZK m | H68: =Model!H38 -> 1885.9221 | I68: =Model!I38 -> 1932.9363 | J68: =Model!J38 -> 2021.2094 | K68: =Model!K38 -> 2104.8627 | L68: =Model!L38 -> 2174.2258
B69: =Inputs!D131 -> Base case | G69: 1 | H69: 1885.9221 | I69: 1932.9363 | J69: 2021.2094 | K69: 2104.8627 | L69: 2174.2258
B70: =Inputs!D132 -> Upside case | G70: 2 | H70: 2006.154 | I70: 2146.474 | J70: 2268.7997 | K70: 2383.4538 | L70: 2476.2881
B71: =Inputs!D133 -> Downside case | G71: 3 | H71: 1621.4213 | I71: 1643.4109 | J71: 1587.2591 | K71: 1637.4863 | L71: 1671.4049
B73: Unlevered free cash flow | C73: CZK m | H73: =Model!H259 -> 48.391829 | I73: =Model!I259 -> 446.55596 | J73: =Model!J259 -> 583.89459 | K73: =Model!K259 -> 674.82263 | L73: =Model!L259 -> 758.47423
B74: =Inputs!D131 -> Base case | G74: 1 | H74: 48.391829 | I74: 446.55596 | J74: 583.89459 | K74: 674.82263 | L74: 758.47423
B75: =Inputs!D132 -> Upside case | G75: 2 | H75: 153.27993 | I75: 669.08943 | J75: 837.87719 | K75: 944.92432 | L75: 973.23901
B76: =Inputs!D133 -> Downside case | G76: 3 | H76: -52.791072 | I76: 279.03192 | J76: 387.50196 | K76: 452.59351 | L76: 513.93703
B78: EPS | C78: CZK | H78: =Model!H76 -> 21.386269 | I78: =Model!I76 -> 17.615873 | J78: =Model!J76 -> 18.634327 | K78: =Model!K76 -> 20.364786 | L78: =Model!L76 -> 22.017323
B79: =Inputs!D131 -> Base case | G79: 1 | H79: 21.386269 | I79: 17.615873 | J79: 18.634327 | K79: 20.364786 | L79: 22.017323
B80: =Inputs!D132 -> Upside case | G80: 2 | H80: 25.34821 | I80: 24.995395 | J80: 27.935337 | K80: 31.450977 | L80: 34.60289
B81: =Inputs!D133 -> Downside case | G81: 3 | H81: 12.670303 | I81: 8.1250156 | J81: 4.8063047 | K81: 6.1504654 | L81: 7.2023856
B83: Net debt / adjusted EBITDA | C83: x | H83: =Model!H221 -> 3.5315344 | I83: =Model!I221 -> 3.59621 | J83: =Model!J221 -> 3.5204172 | K83: =Model!K221 -> 3.4182127 | L83: =Model!L221 -> 3.3085778
B84: =Inputs!D131 -> Base case | G84: 1 | H84: 3.5315344 | I84: 3.59621 | J84: 3.5204172 | K84: 3.4182127 | L84: 3.3085778
B85: =Inputs!D132 -> Upside case | G85: 2 | H85: 3.267601 | I85: 3.084125 | J85: 2.8729433 | K85: 2.6455305 | L85: 2.4459359
B86: =Inputs!D133 -> Downside case | G86: 3 | H86: 4.1700339 | I86: 4.2527124 | J86: 4.4832942 | K86: 4.3864068 | L86: 4.3019082
B88: Debt service cover | C88: x | H88: =Model!H227 -> 3.1068171 | I88: =Model!I227 -> 2.7666641 | J88: =Model!J227 -> 2.8363564 | K88: =Model!K227 -> 2.9114901 | L88: =Model!L227 -> 2.967143
B89: =Inputs!D131 -> Base case | G89: 1 | H89: 3.1068171 | I89: 2.7666641 | J89: 2.8363564 | K89: 2.9114901 | L89: 2.967143
B90: =Inputs!D132 -> Upside case | G90: 2 | H90: 3.2454768 | I90: 2.9957266 | J90: 3.1571551 | K90: 3.3096651 | L90: 3.4435817
B91: =Inputs!D133 -> Downside case | G91: 3 | H91: 2.8462723 | I91: 2.4072816 | J91: 2.356519 | K91: 2.4329304 | L91: 2.4715328
B93: Capex / adjusted EBITDA | C93: % | H93: =Model!H228 -> 0.6097561 | I93: =Model!I228 -> 0.52795031 | J93: =Model!J228 -> 0.46296296 | K93: =Model!K228 -> 0.42944785 | L93: =Model!L228 -> 0.39877301
B94: =Inputs!D131 -> Base case | G94: 1 | H94: 0.6097561 | I94: 0.52795031 | J94: 0.46296296 | K94: 0.42944785 | L94: 0.39877301
B95: =Inputs!D132 -> Upside case | G95: 2 | H95: 0.55555556 | I95: 0.43352601 | J95: 0.37356322 | K95: 0.34285714 | L95: 0.34285714
B96: =Inputs!D133 -> Downside case | G96: 3 | H96: 0.68965517 | I96: 0.59027778 | J96: 0.52447552 | K96: 0.48951049 | L96: 0.45454545
B98: Sensitivity analysis
B101: WACC step | D101: 0.005
B102: Terminal growth step | D102: 0.005
B103: Exit multiple step | D103: 1
B105: Perpetuity growth method
B106: Enterprise value | C106: CZK m | E106: Terminal growth rate →
D107: =Model!D291 -> 15717.161 | E107: =F107-$D$102 -> 0.01 | F107: =G107-$D$102 -> 0.015 | G107: 0.02 | H107: =G107+$D$102 -> 0.025 | I107: =H107+$D$102 -> 0.03
C108: WACC ↓ | D108: =D109-$D$101 -> 0.055735342 | E108: 16141.839 | F108: 17871.231 | G108: 20084.567 | H108: 23018.029 | I108: 27091.35
D109: =D110-$D$101 -> 0.060735342 | E109: 14558.573 | F109: 15927.521 | G109: 17632.528 | H109: 19814.655 | I109: 22706.756
D110: =Inputs!$D$123 -> 0.065735342 | E110: 13259.859 | F110: 14367.426 | G110: 15717.161 | H110: 17398.239 | I110: 19549.742
D111: =D110+$D$101 -> 0.070735342 | E111: 12175.409 | F111: 13087.693 | G111: 14179.788 | H111: 15510.669 | I111: 17168.264
D112: =D111+$D$101 -> 0.075735342 | E112: 11256.323 | F112: 12019.07 | G112: 12918.669 | H112: 13995.579 | I112: 15307.955
B114: Equity value per share | C114: CZK | E114: Terminal growth rate →
E115: =E$107 -> 0.01 | F115: =F$107 -> 0.015 | G115: =G$107 -> 0.02 | H115: =H$107 -> 0.025 | I115: =I$107 -> 0.03
C116: WACC ↓ | D116: =$D108 -> 0.055735342 | E116: =(E108+SUM(Model!$D$292:$D$295))/SharesOut -> 435.61374 | F116: =(F108+SUM(Model!$D$292:$D$295))/SharesOut -> 516.67745 | G116: =(G108+SUM(Model!$D$292:$D$295))/SharesOut -> 620.42563 | H116: =(H108+SUM(Model!$D$292:$D$295))/SharesOut -> 757.92914 | I116: =(I108+SUM(Model!$D$292:$D$295))/SharesOut -> 948.86249
D117: =$D109 -> 0.060735342 | E117: =(E109+SUM(Model!$D$292:$D$295))/SharesOut -> 361.39951 | F117: =(F109+SUM(Model!$D$292:$D$295))/SharesOut -> 425.56775 | G117: =(G109+SUM(Model!$D$292:$D$295))/SharesOut -> 505.48845 | H117: =(H109+SUM(Model!$D$292:$D$295))/SharesOut -> 607.77376 | I117: =(I109+SUM(Model!$D$292:$D$295))/SharesOut -> 743.33846
D118: =$D110 -> 0.065735342 | E118: =(E110+SUM(Model!$D$292:$D$295))/SharesOut -> 300.52341 | F118: =(F110+SUM(Model!$D$292:$D$295))/SharesOut -> 352.43964 | G118: =(G110+SUM(Model!$D$292:$D$295))/SharesOut -> 415.70732 | H118: =(H110+SUM(Model!$D$292:$D$295))/SharesOut -> 494.5064 | I118: =(I110+SUM(Model!$D$292:$D$295))/SharesOut -> 595.35621
D119: =$D111 -> 0.070735342 | E119: =(E111+SUM(Model!$D$292:$D$295))/SharesOut -> 249.6908 | F119: =(F111+SUM(Model!$D$292:$D$295))/SharesOut -> 292.45327 | G119: =(G111+SUM(Model!$D$292:$D$295))/SharesOut -> 343.64428 | H119: =(H111+SUM(Model!$D$292:$D$295))/SharesOut -> 406.02817 | I119: =(I111+SUM(Model!$D$292:$D$295))/SharesOut -> 483.7265
D120: =$D112 -> 0.075735342 | E120: =(E112+SUM(Model!$D$292:$D$295))/SharesOut -> 206.60945 | F120: =(F112+SUM(Model!$D$292:$D$295))/SharesOut -> 242.36254 | G120: =(G112+SUM(Model!$D$292:$D$295))/SharesOut -> 284.53043 | H120: =(H112+SUM(Model!$D$292:$D$295))/SharesOut -> 335.00966 | I120: =(I112+SUM(Model!$D$292:$D$295))/SharesOut -> 396.52614
B122: Upside / (downside) vs share price | C122: % | E122: Terminal growth rate →
E123: =E$107 -> 0.01 | F123: =F$107 -> 0.015 | G123: =G$107 -> 0.02 | H123: =H$107 -> 0.025 | I123: =I$107 -> 0.03
C124: WACC ↓ | D124: =$D108 -> 0.055735342 | E124: =E116/Inputs!$D$113-1 -> -0.11640215 | F124: =F116/Inputs!$D$113-1 -> 0.048027287 | G124: =G116/Inputs!$D$113-1 -> 0.25846983 | H124: =H116/Inputs!$D$113-1 -> 0.53738162 | I124: =I116/Inputs!$D$113-1 -> 0.92467036
D125: =$D109 -> 0.060735342 | E125: =E117/Inputs!$D$113-1 -> -0.26693811 | F125: =F117/Inputs!$D$113-1 -> -0.13677942 | G125: =G117/Inputs!$D$113-1 -> 0.02533154 | H125: =H117/Inputs!$D$113-1 -> 0.23280682 | I125: =I117/Inputs!$D$113-1 -> 0.50778593
D126: =$D110 -> 0.065735342 | E126: =E118/Inputs!$D$113-1 -> -0.39041904 | F126: =F118/Inputs!$D$113-1 -> -0.28511229 | G126: =G118/Inputs!$D$113-1 -> -0.15678028 | H126: =H118/Inputs!$D$113-1 -> 0.0030555689 | I126: =I118/Inputs!$D$113-1 -> 0.20761909
...

Sheet Inputs
B1: Kofola ČeskoSlovensko | Inputs
B2: CZK m unless stated | F2: Scenario | G2: =ScenarioName -> Base case | J2: Model checks | L2: =ModelChecks -> OK
B4: Fiscal year ending 31 December | D4: =Model!D$4 -> 2022 | E4: =Model!E$4 -> 2023 | F4: =Model!F$4 -> 2024 | G4: =Model!G$4 -> 2025 | H4: =Model!H$4 -> 2026 | I4: =Model!I$4 -> 2027 | J4: =Model!J$4 -> 2028 | K4: =Model!K$4 -> 2029 | L4: =Model!L$4 -> 2030
B5: Period end | D5: =Model!D$5 -> 44926 | E5: =Model!E$5 -> 45291 | F5: =Model!F$5 -> 45657 | G5: =Model!G$5 -> 46022 | H5: =Model!H$5 -> 46387 | I5: =Model!I$5 -> 46752 | J5: =Model!J$5 -> 47118 | K5: =Model!K$5 -> 47483 | L5: =Model!L$5 -> 47848
B6: Actual / forecast | D6: =Model!D$6 -> A | E6: =Model!E$6 -> A | F6: =Model!F$6 -> A | G6: =Model!G$6 -> A | H6: =Model!H$6 -> F | I6: =Model!I$6 -> F | J6: =Model!J$6 -> F | K6: =Model!K$6 -> F | L6: =Model!L$6 -> F
B8: General
B9: First historical year | D9: 2022
B10: Last actual year | D10: 2025
B11: Valuation date | D11: 46203
B12: Czech corporate income tax rate | D12: 0.21
B13: Shares issued | C13: m | D13: 22.291948 | N13: H1 2026 report, note 4.14
B14: Treasury shares held by RADENSKA | C14: m | D14: 0.958217 | N14: H1 2026 report
B15: Shares outstanding at valuation date | C15: m | D15: =D13-D14 -> 21.333731
B17: Scenario drivers
B18: % y/y unless stated | D18: =Model!D$4 -> 2022 | E18: =Model!E$4 -> 2023 | F18: =Model!F$4 -> 2024 | G18: =Model!G$4 -> 2025 | H18: =Model!H$4 -> 2026 | I18: =Model!I$4 -> 2027 | J18: =Model!J$4 -> 2028 | K18: =Model!K$4 -> 2029 | L18: =Model!L$4 -> 2030
B19: Active scenario
B21: Revenue growth by segment
B22: CzechoSlovakia | E22: =Model!E20 -> 0.10091836 | F22: =Model!F20 -> 0.11099327 | G22: =Model!G20 -> -0.067431895
B23: Base | H23: 0.1 | I23: 0.04 | J23: 0.035 | K23: 0.03 | L23: 0.03
B24: Upside | H24: 0.12 | I24: 0.05 | J24: 0.045 | K24: 0.04 | L24: 0.035
B25: Downside | H25: 0.07 | I25: 0.02 | J25: -0.06 | K25: 0.04 | L25: 0.02
B26: Live case | H26: =CHOOSE(Scenario,H23,H24,H25) -> 0.1 | I26: =CHOOSE(Scenario,I23,I24,I25) -> 0.04 | J26: =CHOOSE(Scenario,J23,J24,J25) -> 0.035 | K26: =CHOOSE(Scenario,K23,K24,K25) -> 0.03 | L26: =CHOOSE(Scenario,L23,L24,L25) -> 0.03
B28: Adriatic | E28: =Model!E21 -> 0.071744054 | F28: =Model!F21 -> 0.11108383 | G28: =Model!G21 -> -0.018417013
B29: Base | H29: 0.02 | I29: 0.03 | J29: 0.03 | K29: 0.03 | L29: 0.025
B30: Upside | H30: 0.035 | I30: 0.04 | J30: 0.04 | K30: 0.035 | L30: 0.03
B31: Downside | H31: 0 | I31: 0.01 | J31: 0.01 | K31: 0.015 | L31: 0.015
B32: Live case | H32: =CHOOSE(Scenario,H29,H30,H31) -> 0.02 | I32: =CHOOSE(Scenario,I29,I30,I31) -> 0.03 | J32: =CHOOSE(Scenario,J29,J30,J31) -> 0.03 | K32: =CHOOSE(Scenario,K29,K30,K31) -> 0.03 | L32: =CHOOSE(Scenario,L29,L30,L31) -> 0.025
B34: Fresh & Herbs | E34: =Model!E22 -> 0.17114711 | F34: =Model!F22 -> 0.19827776 | G34: =Model!G22 -> 0.15463543
B35: Base | H35: 0.18 | I35: 0.1 | J35: 0.08 | K35: 0.07 | L35: 0.06
B36: Upside | H36: 0.22 | I36: 0.13 | J36: 0.1 | K36: 0.08 | L36: 0.07
B37: Downside | H37: 0.14 | I37: 0.06 | J37: 0.05 | K37: 0.04 | L37: 0.04
B38: Live case | H38: =CHOOSE(Scenario,H35,H36,H37) -> 0.18 | I38: =CHOOSE(Scenario,I35,I36,I37) -> 0.1 | J38: =CHOOSE(Scenario,J35,J36,J37) -> 0.08 | K38: =CHOOSE(Scenario,K35,K36,K37) -> 0.07 | L38: =CHOOSE(Scenario,L35,L36,L37) -> 0.06
B40: Beers & Ciders | E40: =Model!E23 -> n.m. | F40: =Model!F23 -> n.m. | G40: =Model!G23 -> 0.056352049
B41: Base | H41: -0.04 | I41: 0.015 | J41: 0.02 | K41: 0.02 | L41: 0.02
B42: Upside | H42: -0.02 | I42: 0.03 | J42: 0.03 | K42: 0.03 | L42: 0.025
B43: Downside | H43: -0.07 | I43: -0.01 | J43: 0 | K43: 0 | L43: 0.005
B44: Live case | H44: =CHOOSE(Scenario,H41,H42,H43) -> -0.04 | I44: =CHOOSE(Scenario,I41,I42,I43) -> 0.015 | J44: =CHOOSE(Scenario,J41,J42,J43) -> 0.02 | K44: =CHOOSE(Scenario,K41,K42,K43) -> 0.02 | L44: =CHOOSE(Scenario,L41,L42,L43) -> 0.02
B46: Other revenue inputs
B47: Consolidation adjustments (% of segment revenue) | D47: =Model!D25 -> -0.018801087 | E47: =Model!E25 -> -0.018790005 | F47: =Model!F25 -> -0.021865054 | G47: =Model!G25 -> -0.030687617 | H47: -0.04 | I47: -0.04 | J47: -0.04 | K47: -0.04 | L47: -0.04
B50: Cost drivers (% of revenue)
B51: Materials, energy and COGS | D51: =Model!D43 -> 0.48155051 | E51: =Model!E43 -> 0.44798065 | F51: =Model!F43 -> 0.42301668 | G51: =Model!G43 -> 0.3983811
B52: Base | H52: 0.399 | I52: 0.403 | J52: 0.403 | K52: 0.403 | L52: 0.403
B53: Upside | H53: 0.395 | I53: 0.395 | J53: 0.395 | K53: 0.395 | L53: 0.395
B54: Downside | H54: 0.415 | I54: 0.415 | J54: 0.415 | K54: 0.415 | L54: 0.415
B55: Live case | H55: =CHOOSE(Scenario,H52,H53,H54) -> 0.399 | I55: =CHOOSE(Scenario,I52,I53,I54) -> 0.403 | J55: =CHOOSE(Scenario,J52,J53,J54) -> 0.403 | K55: =CHOOSE(Scenario,K52,K53,K54) -> 0.403 | L55: =CHOOSE(Scenario,L52,L53,L54) -> 0.403
B57: Employee benefits | D57: =Model!D44 -> 0.19172782 | E57: =Model!E44 -> 0.20918636 | F57: =Model!F44 -> 0.2112393 | G57: =Model!G44 -> 0.21412179
B58: Base | H58: 0.223 | I58: 0.222 | J58: 0.221 | K58: 0.22 | L58: 0.22
B59: Upside | H59: 0.22 | I59: 0.218 | J59: 0.217 | K59: 0.216 | L59: 0.216
B60: Downside | H60: 0.226 | I60: 0.227 | J60: 0.228 | K60: 0.228 | L60: 0.228
B61: Live case | H61: =CHOOSE(Scenario,H58,H59,H60) -> 0.223 | I61: =CHOOSE(Scenario,I58,I59,I60) -> 0.222 | J61: =CHOOSE(Scenario,J58,J59,J60) -> 0.221 | K61: =CHOOSE(Scenario,K58,K59,K60) -> 0.22 | L61: =CHOOSE(Scenario,L58,L59,L60) -> 0.22
B63: Other cost inputs (same in all cases)
B64: Services | D64: =Model!D45 -> 0.17437136 | E64: =Model!E45 -> 0.17594463 | F64: =Model!F45 -> 0.18299771 | G64: =Model!G45 -> 0.18886406 | H64: 0.19 | I64: 0.19 | J64: 0.19 | K64: 0.19 | L64: 0.19
B65: Other operating costs | D65: =Model!D46 -> 0.013616398 | E65: =Model!E46 -> 0.025692216 | F65: =Model!F46 -> 0.019235328 | G65: =Model!G46 -> 0.024125729 | H65: 0.024 | I65: 0.024 | J65: 0.024 | K65: 0.024 | L65: 0.024
B66: Other operating income/(expense), net | D66: =(Model!D34+Model!D35)/Model!D29 -> -0.0030263036 | E66: =(Model!E34+Model!E35)/Model!E29 -> 0.0069751762 | F66: =(Model!F34+Model!F35)/Model!F29 -> 0.0094847903 | G66: =(Model!G34+Model!G35)/Model!G29 -> 0.004511486 | H66: 0 | I66: 0 | J66: 0 | K66: 0 | L66: 0
B68: FY2026 EBITDA guidance, low / high (CZK m) | D68: 1800 | E68: 1900 | N68: AR2025, Chairman's statement
B70: Operating assets and working capital
B71: Capex (% of revenue) | D71: =Model!D185 -> 0.05252928 | E71: =Model!E185 -> 0.047995173 | F71: =Model!F185 -> 0.074413508 | G71: =Model!G185 -> 0.11385704
B72: Base | H72: 0.1 | I72: 0.085 | J72: 0.075 | K72: 0.07 | L72: 0.065
B73: Upside | H73: 0.095 | I73: 0.075 | J73: 0.065 | K73: 0.06 | L73: 0.06
B74: Downside | H74: =H72 -> 0.1 | I74: =I72 -> 0.085 | J74: =J72 -> 0.075 | K74: =K72 -> 0.07 | L74: =L72 -> 0.065
B75: Live case | H75: =CHOOSE(Scenario,H72,H73,H74) -> 0.1 | I75: =CHOOSE(Scenario,I72,I73,I74) -> 0.085 | J75: =CHOOSE(Scenario,J72,J73,J74) -> 0.075 | K75: =CHOOSE(Scenario,K72,K73,K74) -> 0.07 | L75: =CHOOSE(Scenario,L72,L73,L74) -> 0.065
B77: Other PP&E inputs (same in all cases)
B78: New leases (% of revenue) | F78: =Model!F186 -> 0.017719891 | G78: =Model!G186 -> 0.020840633 | H78: 0.02 | I78: 0.02 | J78: 0.02 | K78: 0.02 | L78: 0.02
B79: D&A (% of opening PP&E) | E79: =Model!E188 -> 0.17441504 | F79: =Model!F188 -> 0.21651759 | G79: =Model!G188 -> 0.17123607 | H79: 0.17 | I79: 0.17 | J79: 0.17 | K79: 0.17 | L79: 0.17
B81: Working capital days (same in all cases)
B82: Receivable days (on revenue) | C82: days | D82: =Model!D170 -> 46.25433 | E82: =Model!E170 -> 47.039416 | F82: =Model!F170 -> 47.80407 | G82: =Model!G170 -> 45.426045 | H82: 46 | I82: 46 | J82: 46 | K82: 46 | L82: 46
B83: Inventory days (on materials and COGS) | C83: days | D83: =Model!D171 -> 73.766853 | E83: =Model!E171 -> 66.211109 | F83: =Model!F171 -> 73.335876 | G83: =Model!G171 -> 85.877707 | H83: 80 | I83: 80 | J83: 80 | K83: 80 | L83: 80
B84: Payable days (on materials and COGS) | C84: days | D84: =Model!D172 -> 176.4036 | E84: =Model!E172 -> 185.8646 | F84: =Model!F172 -> 201.03022 | G84: =Model!G172 -> 204.41783 | H84: 195 | I84: 195 | J84: 195 | K84: 195 | L84: 195
B86: Financing and tax (same in all cases)
B87: Interest rate on bank loans (% of opening) | H87: 0.05 | I87: 0.05 | J87: 0.05 | K87: 0.05 | L87: 0.05
B88: Interest rate on leases (% of opening) | H88: 0.065 | I88: 0.065 | J88: 0.065 | K88: 0.065 | L88: 0.065
B89: Lease principal repaid (% of opening leases) | H89: 0.36 | I89: 0.36 | J89: 0.36 | K89: 0.36 | L89: 0.36
B90: Interest income on cash (% of opening) | H90: 0.005 | I90: 0.005 | J90: 0.005 | K90: 0.005 | L90: 0.005
B91: Other finance costs (CZK m) | H91: 25 | I91: 25 | J91: 25 | K91: 25 | L91: 25
B92: Minimum cash (CZK m) | H92: 500 | I92: 500 | J92: 500 | K92: 500 | L92: 500
B93: Share of profit of associates (CZK m) | H93: 0 | I93: 0 | J93: 0 | K93: 0 | L93: 0
B94: Effective tax rate | H94: 0.26 | I94: 0.26 | J94: 0.26 | K94: 0.26 | L94: 0.26
B95: NCI share of net profit | H95: 0.05 | I95: 0.05 | J95: 0.05 | K95: 0.05 | L95: 0.05
B97: Dividends (by scenario)
B98: Dividend per share declared for that year (CZK) | D98: =Model!D77 -> 13.5 | E98: =Model!E77 -> 13.5 | F98: =Model!F77 -> 21 | G98: =Model!G77 -> 21
B99: Base | H99: 21 | I99: 21 | J99: 21 | K99: 21 | L99: 21
B100: Upside | H100: 21 | I100: 21 | J100: 21 | K100: 21 | L100: 21
B101: Downside | H101: 10 | I101: 10 | J101: 10 | K101: 10 | L101: 10
B102: Live case | H102: =CHOOSE(Scenario,H99,H100,H101) -> 21 | I102: =CHOOSE(Scenario,I99,I100,I101) -> 21 | J102: =CHOOSE(Scenario,J99,J100,J101) -> 21 | K102: =CHOOSE(Scenario,K99,K100,K101) -> 21 | L102: =CHOOSE(Scenario,L99,L100,L101) -> 21
B104: WACC build
B106: Czech 10-year government bond yield | C106: % | D106: 0.047 | N106: OECD: Czech 10-year government bond yield, June 2026 average
B107: Less: default spread, Czech Republic | C107: % | D107: 0.0051 | N107: Damodaran, January 2026 (Moody's Aa3)
B108: Risk-free rate | C108: % | D108: =D106-D107 -> 0.0419
B109: Mature market equity risk premium | C109: % | D109: 0.042 | N109: Damodaran, July 2026
B110: Country risk premium, Czech Republic | C110: % | D110: 0.0078 | N110: Damodaran, January 2026 (Moody's Aa3)
B111: Total equity risk premium | C111: % | D111: =D109+D110 -> 0.0498
B112: Unlevered beta | C112: x | D112: 0.54 | N112: Damodaran: global Beverage (Soft), January 2026
B113: Share price at 30.06.2026 | C113: CZK | D113: 493 | N113: Prague Stock Exchange closing price, 30.06.2026
B114: Market capitalisation | C114: CZK m | D114: =D113*SharesOut -> 10517.529
B115: Net debt at 30.06.2026 | C115: CZK m | D115: =Hist!E371 -> 6441.73
B116: Net debt / equity | C116: x | D116: =D115/D114 -> 0.61247559
B117: Relevered beta | C117: x | D117: =D112*(1+(1-TaxRate)*D116) -> 0.80128209
B118: Cost of equity | C118: % | D118: =D108+D117*D111 -> 0.081803848
B119: Pre-tax cost of debt | C119: % | D119: =H87 -> 0.05
B120: After-tax cost of debt | C120: % | D120: =D119*(1-TaxRate) -> 0.0395
...

Sheet Model
B1: Kofola ČeskoSlovensko | Model
B2: CZK m unless stated | F2: Scenario | G2: =ScenarioName -> Base case | J2: Model checks | L2: =ModelChecks -> OK
B4: Fiscal year ending 31 December | D4: =FirstYear -> 2022 | E4: =D4+1 -> 2023 | F4: =E4+1 -> 2024 | G4: =F4+1 -> 2025 | H4: =G4+1 -> 2026 | I4: =H4+1 -> 2027 | J4: =I4+1 -> 2028 | K4: =J4+1 -> 2029 | L4: =K4+1 -> 2030
B5: Period end | D5: =DATE(D4,12,31) -> 44926 | E5: =DATE(E4,12,31) -> 45291 | F5: =DATE(F4,12,31) -> 45657 | G5: =DATE(G4,12,31) -> 46022 | H5: =DATE(H4,12,31) -> 46387 | I5: =DATE(I4,12,31) -> 46752 | J5: =DATE(J4,12,31) -> 47118 | K5: =DATE(K4,12,31) -> 47483 | L5: =DATE(L4,12,31) -> 47848
B6: Actual / forecast | D6: =IF(D$4<=LastActual,"A","F") -> A | E6: =IF(E$4<=LastActual,"A","F") -> A | F6: =IF(F$4<=LastActual,"A","F") -> A | G6: =IF(G$4<=LastActual,"A","F") -> A | H6: =IF(H$4<=LastActual,"A","F") -> F | I6: =IF(I$4<=LastActual,"A","F") -> F | J6: =IF(J$4<=LastActual,"A","F") -> F | K6: =IF(K$4<=LastActual,"A","F") -> F | L6: =IF(L$4<=LastActual,"A","F") -> F
B8: Revenue schedule
B9: CZK m | D9: =D$4 -> 2022 | E9: =E$4 -> 2023 | F9: =F$4 -> 2024 | G9: =G$4 -> 2025 | H9: =H$4 -> 2026 | I9: =I$4 -> 2027 | J9: =J$4 -> 2028 | K9: =K$4 -> 2029 | L9: =L$4 -> 2030
B10: Segment revenue, incl. inter-segment sales
B11: CzechoSlovakia | D11: =Hist!D149 -> 5735.854 | E11: =Hist!E149 -> 6314.707 | F11: =Hist!F149 -> 7015.597 | G11: =Hist!G149 -> 6542.522 | H11: =G11*(1+Inputs!H26) -> 7196.7742 | I11: =H11*(1+Inputs!I26) -> 7484.6452 | J11: =I11*(1+Inputs!J26) -> 7746.6077 | K11: =J11*(1+Inputs!K26) -> 7979.006 | L11: =K11*(1+Inputs!L26) -> 8218.3762
B12: Adriatic | D12: =Hist!D150 -> 1413.483 | E12: =Hist!E150 -> 1514.892 | F12: =Hist!F150 -> 1683.172 | G12: =Hist!G150 -> 1652.173 | H12: =G12*(1+Inputs!H32) -> 1685.2165 | I12: =H12*(1+Inputs!I32) -> 1735.773 | J12: =I12*(1+Inputs!J32) -> 1787.8461 | K12: =J12*(1+Inputs!K32) -> 1841.4815 | L12: =K12*(1+Inputs!L32) -> 1887.5186
B13: Fresh & Herbs | D13: =Hist!D151 -> 876.848 | E13: =Hist!E151 -> 1026.918 | F13: =Hist!F151 -> 1230.533 | G13: =Hist!G151 -> 1420.817 | H13: =G13*(1+Inputs!H38) -> 1676.5641 | I13: =H13*(1+Inputs!I38) -> 1844.2205 | J13: =I13*(1+Inputs!J38) -> 1991.7581 | K13: =J13*(1+Inputs!K38) -> 2131.1812 | L13: =K13*(1+Inputs!L38) -> 2259.052
B14: Beers & Ciders | D14: =Hist!D152 -> 0 | E14: =Hist!E152 -> 0 | F14: =Hist!F152 -> 1400.375 | G14: =Hist!G152 -> 1479.289 | H14: =G14*(1+Inputs!H44) -> 1420.1174 | I14: =H14*(1+Inputs!I44) -> 1441.4192 | J14: =I14*(1+Inputs!J44) -> 1470.2476 | K14: =J14*(1+Inputs!K44) -> 1499.6525 | L14: =K14*(1+Inputs!L44) -> 1529.6456
B15: Consolidation adjustments | D15: =Hist!D153 -> -150.901 | E15: =Hist!E153 -> -166.414 | F15: =Hist!F153 -> -247.724 | G15: =Hist!G153 -> -340.473 | H15: =Inputs!H47*SUM(H11:H14) -> -479.14689 | I15: =Inputs!I47*SUM(I11:I14) -> -500.24231 | J15: =Inputs!J47*SUM(J11:J14) -> -519.85838 | K15: =Inputs!K47*SUM(K11:K14) -> -538.05285 | L15: =Inputs!L47*SUM(L11:L14) -> -555.78369
B16: Revenue | D16: =SUM(D11:D15) -> 7875.284 | E16: =SUM(E11:E15) -> 8690.103 | F16: =SUM(F11:F15) -> 11081.953 | G16: =SUM(G11:G15) -> 10754.328 | H16: =SUM(H11:H15) -> 11499.525 | I16: =SUM(I11:I15) -> 12005.815 | J16: =SUM(J11:J15) -> 12476.601 | K16: =SUM(K11:K15) -> 12913.268 | L16: =SUM(L11:L15) -> 13338.809
B18: Implied H2 2026 revenue growth | H18: =(H16-Hist!E301)/(G16-Hist!D301)-1 -> 0.040113924
B19: Growth y/y
B20: CzechoSlovakia | E20: =IF(D11=0,"n.m.",E11/D11-1) -> 0.10091836 | F20: =IF(E11=0,"n.m.",F11/E11-1) -> 0.11099327 | G20: =IF(F11=0,"n.m.",G11/F11-1) -> -0.067431895 | H20: =IF(G11=0,"n.m.",H11/G11-1) -> 0.1 | I20: =IF(H11=0,"n.m.",I11/H11-1) -> 0.04 | J20: =IF(I11=0,"n.m.",J11/I11-1) -> 0.035 | K20: =IF(J11=0,"n.m.",K11/J11-1) -> 0.03 | L20: =IF(K11=0,"n.m.",L11/K11-1) -> 0.03
B21: Adriatic | E21: =IF(D12=0,"n.m.",E12/D12-1) -> 0.071744054 | F21: =IF(E12=0,"n.m.",F12/E12-1) -> 0.11108383 | G21: =IF(F12=0,"n.m.",G12/F12-1) -> -0.018417013 | H21: =IF(G12=0,"n.m.",H12/G12-1) -> 0.02 | I21: =IF(H12=0,"n.m.",I12/H12-1) -> 0.03 | J21: =IF(I12=0,"n.m.",J12/I12-1) -> 0.03 | K21: =IF(J12=0,"n.m.",K12/J12-1) -> 0.03 | L21: =IF(K12=0,"n.m.",L12/K12-1) -> 0.025
B22: Fresh & Herbs | E22: =IF(D13=0,"n.m.",E13/D13-1) -> 0.17114711 | F22: =IF(E13=0,"n.m.",F13/E13-1) -> 0.19827776 | G22: =IF(F13=0,"n.m.",G13/F13-1) -> 0.15463543 | H22: =IF(G13=0,"n.m.",H13/G13-1) -> 0.18 | I22: =IF(H13=0,"n.m.",I13/H13-1) -> 0.1 | J22: =IF(I13=0,"n.m.",J13/I13-1) -> 0.08 | K22: =IF(J13=0,"n.m.",K13/J13-1) -> 0.07 | L22: =IF(K13=0,"n.m.",L13/K13-1) -> 0.06
B23: Beers & Ciders | E23: =IF(D14=0,"n.m.",E14/D14-1) -> n.m. | F23: =IF(E14=0,"n.m.",F14/E14-1) -> n.m. | G23: =IF(F14=0,"n.m.",G14/F14-1) -> 0.056352049 | H23: =IF(G14=0,"n.m.",H14/G14-1) -> -0.04 | I23: =IF(H14=0,"n.m.",I14/H14-1) -> 0.015 | J23: =IF(I14=0,"n.m.",J14/I14-1) -> 0.02 | K23: =IF(J14=0,"n.m.",K14/J14-1) -> 0.02 | L23: =IF(K14=0,"n.m.",L14/K14-1) -> 0.02
B24: Revenue | E24: =IF(D16=0,"n.m.",E16/D16-1) -> 0.10346535 | F24: =IF(E16=0,"n.m.",F16/E16-1) -> 0.27523839 | G24: =IF(F16=0,"n.m.",G16/F16-1) -> -0.029563832 | H24: =IF(G16=0,"n.m.",H16/G16-1) -> 0.069292779 | I24: =IF(H16=0,"n.m.",I16/H16-1) -> 0.044027053 | J24: =IF(I16=0,"n.m.",J16/I16-1) -> 0.03921314 | K24: =IF(J16=0,"n.m.",K16/J16-1) -> 0.034998888 | L24: =IF(K16=0,"n.m.",L16/K16-1) -> 0.032953725
B25: Consolidation adjustments (% of segment revenue) | D25: =D15/SUM(D11:D14) -> -0.018801087 | E25: =E15/SUM(E11:E14) -> -0.018790005 | F25: =F15/SUM(F11:F14) -> -0.021865054 | G25: =G15/SUM(G11:G14) -> -0.030687617 | H25: =H15/SUM(H11:H14) -> -0.04 | I25: =I15/SUM(I11:I14) -> -0.04 | J25: =J15/SUM(J11:J14) -> -0.04 | K25: =K15/SUM(K11:K14) -> -0.04 | L25: =L15/SUM(L11:L14) -> -0.04
B27: Cost schedule (by nature)
B28: CZK m | D28: =D$4 -> 2022 | E28: =E$4 -> 2023 | F28: =F$4 -> 2024 | G28: =G$4 -> 2025 | H28: =H$4 -> 2026 | I28: =I$4 -> 2027 | J28: =J$4 -> 2028 | K28: =K$4 -> 2029 | L28: =L$4 -> 2030
B29: Revenue | D29: =D16 -> 7875.284 | E29: =E16 -> 8690.103 | F29: =F16 -> 11081.953 | G29: =G16 -> 10754.328 | H29: =H16 -> 11499.525 | I29: =I16 -> 12005.815 | J29: =J16 -> 12476.601 | K29: =K16 -> 12913.268 | L29: =L16 -> 13338.809
B30: Materials, energy and cost of goods sold | D30: =-Hist!D220 -> -3792.347 | E30: =-Hist!E220 -> -3892.998 | F30: =-Hist!F220 -> -4687.851 | G30: =-Hist!G220 -> -4284.321 | H30: =-H$29*Inputs!H55 -> -4588.3106 | I30: =-I$29*Inputs!I55 -> -4838.3436 | J30: =-J$29*Inputs!J55 -> -5028.0703 | K30: =-K$29*Inputs!K55 -> -5204.0472 | L30: =-L$29*Inputs!L55 -> -5375.5399
B31: Employee benefits | D31: =-Hist!D219 -> -1509.911 | E31: =-Hist!E219 -> -1817.851 | F31: =-Hist!F219 -> -2340.944 | G31: =-Hist!G219 -> -2302.736 | H31: =-H$29*Inputs!H61 -> -2564.3941 | I31: =-I$29*Inputs!I61 -> -2665.291 | J31: =-J$29*Inputs!J61 -> -2757.3289 | K31: =-K$29*Inputs!K61 -> -2840.919 | L31: =-L$29*Inputs!L61 -> -2934.5379
B32: Services | D32: =-Hist!D221 -> -1373.224 | E32: =-Hist!E221 -> -1528.977 | F32: =-Hist!F221 -> -2027.972 | G32: =-Hist!G221 -> -2031.106 | H32: =-H$29*Inputs!H64 -> -2184.9098 | I32: =-I$29*Inputs!I64 -> -2281.1049 | J32: =-J$29*Inputs!J64 -> -2370.5542 | K32: =-K$29*Inputs!K64 -> -2453.521 | L32: =-L$29*Inputs!L64 -> -2534.3736
B33: Other operating costs | D33: =-SUM(Hist!D222:D228) -> -107.233 | E33: =-SUM(Hist!E222:E228) -> -223.268 | F33: =-SUM(Hist!F222:F228) -> -213.165 | G33: =-SUM(Hist!G222:G228) -> -259.456 | H33: =-H$29*Inputs!H65 -> -275.98861 | I33: =-I$29*Inputs!I65 -> -288.13957 | J33: =-J$29*Inputs!J65 -> -299.43843 | K33: =-K$29*Inputs!K65 -> -309.91844 | L33: =-L$29*Inputs!L65 -> -320.13141
B34: Other operating income | D34: =Hist!D12 -> 47.858 | E34: =Hist!E12 -> 89.917 | F34: =Hist!F12 -> 271.889 | G34: =Hist!G12 -> 152.164 | H34: =H$29*Inputs!H66 -> 0 | I34: =I$29*Inputs!I66 -> 0 | J34: =J$29*Inputs!J66 -> 0 | K34: =K$29*Inputs!K66 -> 0 | L34: =L$29*Inputs!L66 -> 0
B35: Other operating expenses (excl. D&A) | D35: =Hist!D13-Hist!D230 -> -71.691 | E35: =Hist!E13-Hist!E230 -> -29.302 | F35: =Hist!F13-Hist!F230 -> -166.779 | G35: =Hist!G13-Hist!G230 -> -103.646 | H35: =0 -> 0 | I35: =0 -> 0 | J35: =0 -> 0 | K35: =0 -> 0 | L35: =0 -> 0
B36: EBITDA | D36: =SUM(D29:D35) -> 1068.736 | E36: =SUM(E29:E35) -> 1287.624 | F36: =SUM(F29:F35) -> 1917.131 | G36: =SUM(G29:G35) -> 1925.227 | H36: =SUM(H29:H35) -> 1885.9221 | I36: =SUM(I29:I35) -> 1932.9363 | J36: =SUM(J29:J35) -> 2021.2094 | K36: =SUM(K29:K35) -> 2104.8627 | L36: =SUM(L29:L35) -> 2174.2258
B37: One-off items | D37: =Hist!D34 -> 41.695 | E37: =Hist!E34 -> -34.22 | F37: =Hist!F34 -> -66.138 | G37: =Hist!G34 -> -108.784 | H37: =0 -> 0 | I37: =0 -> 0 | J37: =0 -> 0 | K37: =0 -> 0 | L37: =0 -> 0
B38: Adjusted EBITDA | D38: =D36+D37 -> 1110.431 | E38: =E36+E37 -> 1253.404 | F38: =F36+F37 -> 1850.993 | G38: =G36+G37 -> 1816.443 | H38: =H36+H37 -> 1885.9221 | I38: =I36+I37 -> 1932.9363 | J38: =J36+J37 -> 2021.2094 | K38: =K36+K37 -> 2104.8627 | L38: =L36+L37 -> 2174.2258
B39: Check: EBITDA vs reported EBIT + D&A | D39: =ROUND(D36-(Hist!D36+Hist!D94),1) -> 0 | E39: =ROUND(E36-(Hist!E36+Hist!E94),1) -> 0 | F39: =ROUND(F36-(Hist!F36+Hist!F94),1) -> 0 | G39: =ROUND(G36-(Hist!G36+Hist!G94),1) -> 0
B40: Check: FY2026F adjusted EBITDA within guidance (CZK 1.8 to 1.9bn) | H40: =IF(AND(H38>=GuideLow,H38<=GuideHigh),0,1) -> 0
B41: Implied H2 2026 adjusted EBITDA growth | H41: =(H38-Hist!E323)/(G38-Hist!D323)-1 -> -0.033561155
B42: Cost ratios and margins (% of revenue)
B43: Materials, energy and COGS | D43: =-D30/D29 -> 0.48155051 | E43: =-E30/E29 -> 0.44798065 | F43: =-F30/F29 -> 0.42301668 | G43: =-G30/G29 -> 0.3983811 | H43: =-H30/H29 -> 0.399 | I43: =-I30/I29 -> 0.403 | J43: =-J30/J29 -> 0.403 | K43: =-K30/K29 -> 0.403 | L43: =-L30/L29 -> 0.403
B44: Employee benefits | D44: =-D31/D29 -> 0.19172782 | E44: =-E31/E29 -> 0.20918636 | F44: =-F31/F29 -> 0.2112393 | G44: =-G31/G29 -> 0.21412179 | H44: =-H31/H29 -> 0.223 | I44: =-I31/I29 -> 0.222 | J44: =-J31/J29 -> 0.221 | K44: =-K31/K29 -> 0.22 | L44: =-L31/L29 -> 0.22
B45: Services | D45: =-D32/D29 -> 0.17437136 | E45: =-E32/E29 -> 0.17594463 | F45: =-F32/F29 -> 0.18299771 | G45: =-G32/G29 -> 0.18886406 | H45: =-H32/H29 -> 0.19 | I45: =-I32/I29 -> 0.19 | J45: =-J32/J29 -> 0.19 | K45: =-K32/K29 -> 0.19 | L45: =-L32/L29 -> 0.19
B46: Other operating costs | D46: =-D33/D29 -> 0.013616398 | E46: =-E33/E29 -> 0.025692216 | F46: =-F33/F29 -> 0.019235328 | G46: =-G33/G29 -> 0.024125729 | H46: =-H33/H29 -> 0.024 | I46: =-I33/I29 -> 0.024 | J46: =-J33/J29 -> 0.024 | K46: =-K33/K29 -> 0.024 | L46: =-L33/L29 -> 0.024
B47: EBITDA margin | D47: =D36/D29 -> 0.13570761 | E47: =E36/E29 -> 0.14817132 | F47: =F36/F29 -> 0.17299577 | G47: =G36/G29 -> 0.17901881 | H47: =H36/H29 -> 0.164 | I47: =I36/I29 -> 0.161 | J47: =J36/J29 -> 0.162 | K47: =K36/K29 -> 0.163 | L47: =L36/L29 -> 0.163
B48: Adjusted EBITDA margin | D48: =D38/D29 -> 0.14100203 | E48: =E38/E29 -> 0.1442335 | F48: =F38/F29 -> 0.16702769 | G48: =G38/G29 -> 0.16890344 | H48: =H38/H29 -> 0.164 | I48: =I38/I29 -> 0.161 | J48: =J38/J29 -> 0.162 | K48: =K38/K29 -> 0.163 | L48: =L38/L29 -> 0.163
B50: Adjusted EBITDA margin by segment (% of segment revenue)
B51: CzechoSlovakia | D51: =IF(Hist!D149=0,"n.m.",(Hist!D162+Hist!D169+Hist!D175)/Hist!D149) -> 0.15257432 | E51: =IF(Hist!E149=0,"n.m.",(Hist!E162+Hist!E169+Hist!E175)/Hist!E149) -> 0.14854228 | F51: =IF(Hist!F149=0,"n.m.",(Hist!F162+Hist!F169+Hist!F175)/Hist!F149) -> 0.16609677 | G51: =IF(Hist!G149=0,"n.m.",(Hist!G162+Hist!G169+Hist!G175)/Hist!G149) -> 0.18964888
B52: Adriatic | D52: =IF(Hist!D150=0,"n.m.",(Hist!D163+Hist!D170+Hist!D176)/Hist!D150) -> 0.12859299 | E52: =IF(Hist!E150=0,"n.m.",(Hist!E163+Hist!E170+Hist!E176)/Hist!E150) -> 0.13513967 | F52: =IF(Hist!F150=0,"n.m.",(Hist!F163+Hist!F170+Hist!F176)/Hist!F150) -> 0.15914892 | G52: =IF(Hist!G150=0,"n.m.",(Hist!G163+Hist!G170+Hist!G176)/Hist!G150) -> 0.15436095
B53: Fresh & Herbs | D53: =IF(Hist!D151=0,"n.m.",(Hist!D164+Hist!D171+Hist!D177)/Hist!D151) -> 0.061040226 | E53: =IF(Hist!E151=0,"n.m.",(Hist!E164+Hist!E171+Hist!E177)/Hist!E151) -> 0.10777978 | F53: =IF(Hist!F151=0,"n.m.",(Hist!F164+Hist!F171+Hist!F177)/Hist!F151) -> 0.11655193 | G53: =IF(Hist!G151=0,"n.m.",(Hist!G164+Hist!G171+Hist!G177)/Hist!G151) -> 0.10243754
B54: Beers & Ciders | D54: =IF(Hist!D152=0,"n.m.",(Hist!D165+Hist!D172+Hist!D178)/Hist!D152) -> n.m. | E54: =IF(Hist!E152=0,"n.m.",(Hist!E165+Hist!E172+Hist!E178)/Hist!E152) -> n.m. | F54: =IF(Hist!F152=0,"n.m.",(Hist!F165+Hist!F172+Hist!F178)/Hist!F152) -> 0.19589681 | G54: =IF(Hist!G152=0,"n.m.",(Hist!G165+Hist!G172+Hist!G178)/Hist!G152) -> 0.11835821
B56: Income statement
B57: CZK m | D57: =D$4 -> 2022 | E57: =E$4 -> 2023 | F57: =F$4 -> 2024 | G57: =G$4 -> 2025 | H57: =H$4 -> 2026 | I57: =I$4 -> 2027 | J57: =J$4 -> 2028 | K57: =K$4 -> 2029 | L57: =L$4 -> 2030
B58: Revenue | D58: =D16 -> 7875.284 | E58: =E16 -> 8690.103 | F58: =F16 -> 11081.953 | G58: =G16 -> 10754.328 | H58: =H16 -> 11499.525 | I58: =I16 -> 12005.815 | J58: =J16 -> 12476.601 | K58: =K16 -> 12913.268 | L58: =L16 -> 13338.809
B59: Operating costs, net (excl. D&A) | D59: =SUM(D30:D35) -> -6806.548 | E59: =SUM(E30:E35) -> -7402.479 | F59: =SUM(F30:F35) -> -9164.822 | G59: =SUM(G30:G35) -> -8829.101 | H59: =SUM(H30:H35) -> -9613.6031 | I59: =SUM(I30:I35) -> -10072.879 | J59: =SUM(J30:J35) -> -10455.392 | K59: =SUM(K30:K35) -> -10808.406 | L59: =SUM(L30:L35) -> -11164.583
B60: EBITDA | D60: =SUM(D58:D59) -> 1068.736 | E60: =SUM(E58:E59) -> 1287.624 | F60: =SUM(F58:F59) -> 1917.131 | G60: =SUM(G58:G59) -> 1925.227 | H60: =SUM(H58:H59) -> 1885.9221 | I60: =SUM(I58:I59) -> 1932.9363 | J60: =SUM(J58:J59) -> 2021.2094 | K60: =SUM(K58:K59) -> 2104.8627 | L60: =SUM(L58:L59) -> 2174.2258
B61: Depreciation and amortisation | D61: =-Hist!D94 -> -586.096 | E61: =-Hist!E94 -> -540.421 | F61: =-Hist!F94 -> -674.076 | G61: =-Hist!G94 -> -760.644 | H61: =H179 -> -900.94951 | I61: =I179 -> -1007.0101 | J61: =J179 -> -1050.1222 | K61: =K179 -> -1073.0985 | L61: =L179 -> -1088.2448
B62: EBIT | D62: =SUM(D60:D61) -> 482.64 | E62: =SUM(E60:E61) -> 747.203 | F62: =SUM(F60:F61) -> 1243.055 | G62: =SUM(G60:G61) -> 1164.583 | H62: =SUM(H60:H61) -> 984.97263 | I62: =SUM(I60:I61) -> 925.9262 | J62: =SUM(J60:J61) -> 971.08721 | K62: =SUM(K60:K61) -> 1031.7642 | L62: =SUM(L60:L61) -> 1085.981
B63: Finance income | D63: =Hist!D15 -> 158.282 | E63: =Hist!E15 -> 34.256 | F63: =Hist!F15 -> 46.197 | G63: =Hist!G15 -> 84.532 | H63: =H213 -> 3.17359 | I63: =I213 -> 2.5 | J63: =J213 -> 2.5 | K63: =K213 -> 2.5 | L63: =L213 -> 2.5
B64: Finance costs | D64: =Hist!D16 -> -241.078 | E64: =Hist!E16 -> -295.532 | F64: =Hist!F16 -> -361.47 | G64: =Hist!G16 -> -314.448 | H64: =H214 -> -339.14351 | I64: =I214 -> -393.84257 | J64: =J214 -> -408.09687 | K64: =K214 -> -416.26015 | L64: =L214 -> -420.3279
B65: Share of profit of equity-accounted investees | D65: =Hist!D17 -> 0 | E65: =Hist!E17 -> -3.985 | F65: =Hist!F17 -> -0.482 | G65: =Hist!G17 -> -1.758 | H65: =Inputs!H93 -> 0 | I65: =Inputs!I93 -> 0 | J65: =Inputs!J93 -> 0 | K65: =Inputs!K93 -> 0 | L65: =Inputs!L93 -> 0
B66: Profit before tax | D66: =SUM(D62:D65) -> 399.844 | E66: =SUM(E62:E65) -> 481.942 | F66: =SUM(F62:F65) -> 927.3 | G66: =SUM(G62:G65) -> 932.909 | H66: =SUM(H62:H65) -> 649.00271 | I66: =SUM(I62:I65) -> 534.58363 | J66: =SUM(J62:J65) -> 565.49034 | K66: =SUM(K62:K65) -> 618.00407 | L66: =SUM(L62:L65) -> 668.15314
B67: Income tax expense | D67: =Hist!D19 -> -135.925 | E67: =Hist!E19 -> -112.965 | F67: =Hist!F19 -> -274.149 | G67: =Hist!G19 -> -251.321 | H67: =-H66*Inputs!H94 -> -168.74071 | I67: =-I66*Inputs!I94 -> -138.99174 | J67: =-J66*Inputs!J94 -> -147.02749 | K67: =-K66*Inputs!K94 -> -160.68106 | L67: =-L66*Inputs!L94 -> -173.71982
B68: Net profit | D68: =SUM(D66:D67) -> 263.919 | E68: =SUM(E66:E67) -> 368.977 | F68: =SUM(F66:F67) -> 653.151 | G68: =SUM(G66:G67) -> 681.588 | H68: =SUM(H66:H67) -> 480.26201 | I68: =SUM(I66:I67) -> 395.59188 | J68: =SUM(J66:J67) -> 418.46285 | K68: =SUM(K66:K67) -> 457.32301 | L68: =SUM(L66:L67) -> 494.43332
B69: Non-controlling interests | D69: =-Hist!D22 -> 5.231 | E69: =-Hist!E22 -> -3.58 | F69: =-Hist!F22 -> -55.26 | G69: =-Hist!G22 -> -7.665 | H69: =-H68*Inputs!H95 -> -24.0131 | I69: =-I68*Inputs!I95 -> -19.779594 | J69: =-J68*Inputs!J95 -> -20.923143 | K69: =-K68*Inputs!K95 -> -22.866151 | L69: =-L68*Inputs!L95 -> -24.721666
B70: Net profit attributable to owners | D70: =SUM(D68:D69) -> 269.15 | E70: =SUM(E68:E69) -> 365.397 | F70: =SUM(F68:F69) -> 597.891 | G70: =SUM(G68:G69) -> 673.923 | H70: =SUM(H68:H69) -> 456.24891 | I70: =SUM(I68:I69) -> 375.81229 | J70: =SUM(J68:J69) -> 397.53971 | K70: =SUM(K68:K69) -> 434.45686 | L70: =SUM(L68:L69) -> 469.71165
B71: Check: net profit vs reported | D71: =ROUND(D68-Hist!D37,1) -> 0 | E71: =ROUND(E68-Hist!E37,1) -> 0 | F71: =ROUND(F68-Hist!F37,1) -> 0 | G71: =ROUND(G68-Hist!G37,1) -> 0
B74: Memo
B75: Adjusted EBITDA | D75: =D38 -> 1110.431 | E75: =E38 -> 1253.404 | F75: =F38 -> 1850.993 | G75: =G38 -> 1816.443 | H75: =H38 -> 1885.9221 | I75: =I38 -> 1932.9363 | J75: =J38 -> 2021.2094 | K75: =K38 -> 2104.8627 | L75: =L38 -> 2174.2258
B76: Basic EPS, reported | C76: CZK | D76: =Hist!D25 -> 12.07 | E76: =Hist!E25 -> 16.39 | F76: =Hist!F25 -> 26.82 | G76: =Hist!G25 -> 30.23 | H76: =H70/H78 -> 21.386269 | I76: =I70/I78 -> 17.615873 | J76: =J70/J78 -> 18.634327 | K76: =K70/K78 -> 20.364786 | L76: =L70/L78 -> 22.017323
B77: Dividend per share declared for the year | C77: CZK | D77: =Hist!D27 -> 13.5 | E77: =Hist!E27 -> 13.5 | F77: =Hist!F27 -> 21 | G77: =Hist!G27 -> 21 | H77: =Inputs!H102 -> 21 | I77: =Inputs!I102 -> 21 | J77: =Inputs!J102 -> 21 | K77: =Inputs!K102 -> 21 | L77: =Inputs!L102 -> 21
B78: Shares outstanding, year end | C78: m | D78: =Hist!D30 -> 21.229712 | E78: =Hist!E30 -> 21.229712 | F78: =Hist!F30 -> 21.266682 | G78: =Hist!G30 -> 21.293526 | H78: =SharesOut -> 21.333731 | I78: =SharesOut -> 21.333731 | J78: =SharesOut -> 21.333731 | K78: =SharesOut -> 21.333731 | L78: =SharesOut -> 21.333731
B80: Balance sheet
B81: CZK m | D81: =D$4 -> 2022 | E81: =E$4 -> 2023 | F81: =F$4 -> 2024 | G81: =G$4 -> 2025 | H81: =H$4 -> 2026 | I81: =I$4 -> 2027 | J81: =J$4 -> 2028 | K81: =K$4 -> 2029 | L81: =L$4 -> 2030
B82: Assets
B83: Cash and cash equivalents | D83: =Hist!D55 -> 626.442 | E83: =Hist!E55 -> 1071.099 | F83: =Hist!F55 -> 1229.999 | G83: =Hist!G55 -> 634.718 | H83: =H143 -> 500 | I83: =I143 -> 500 | J83: =J143 -> 500 | K83: =K143 -> 500 | L83: =L143 -> 500
B84: Trade and other receivables | D84: =Hist!D53 -> 997.989 | E84: =Hist!E53 -> 1119.938 | F84: =Hist!F53 -> 1451.404 | G84: =Hist!G53 -> 1338.429 | H84: =H164 -> 1449.2552 | I84: =I164 -> 1513.0617 | J84: =J164 -> 1572.3936 | K84: =K164 -> 1627.4256 | L84: =L164 -> 1681.0553
B85: Inventories | D85: =Hist!D52 -> 766.437 | E85: =Hist!E52 -> 706.191 | F85: =Hist!F52 -> 941.884 | G85: =Hist!G52 -> 1008.021 | H85: =H165 -> 1005.6571 | I85: =I165 -> 1060.4589 | J85: =J165 -> 1102.0428 | K85: =K165 -> 1140.6131 | L85: =L165 -> 1178.2005
B86: Other current assets | D86: =Hist!D54 -> 23.635 | E86: =Hist!E54 -> 0.125 | F86: =Hist!F54 -> 3.556 | G86: =Hist!G54 -> 80.773 | H86: =G86 -> 80.773 | I86: =H86 -> 80.773 | J86: =I86 -> 80.773 | K86: =J86 -> 80.773 | L86: =K86 -> 80.773
B87: Total current assets | D87: =SUM(D83:D86) -> 2414.503 | E87: =SUM(E83:E86) -> 2897.353 | F87: =SUM(F83:F86) -> 3626.843 | G87: =SUM(G83:G86) -> 3061.941 | H87: =SUM(H83:H86) -> 3035.6854 | I87: =SUM(I83:I86) -> 3154.2936 | J87: =SUM(J83:J86) -> 3255.2094 | K87: =SUM(K83:K86) -> 3348.8117 | L87: =SUM(L83:L86) -> 3440.0289
B88: PP&E incl. right-of-use assets | D88: =Hist!D41+Hist!D42 -> 3098.477 | E88: =Hist!E41+Hist!E42 -> 3113.262 | F88: =Hist!F41+Hist!F42 -> 4442.078 | G88: =Hist!G41+Hist!G42 -> 5299.703 | H88: =H181 -> 5923.5888 | I88: =I181 -> 6177.1893 | J88: =J181 -> 6312.3442 | K88: =K181 -> 6401.4399 | L88: =L181 -> 6446.9938
B89: Goodwill and intangible assets | D89: =Hist!D43+Hist!D44 -> 1825.661 | E89: =Hist!E43+Hist!E44 -> 1822.114 | F89: =Hist!F43+Hist!F44 -> 2449.747 | G89: =Hist!G43+Hist!G44 -> 2763.976 | H89: =H182 -> 2955.347 | I89: =I182 -> 2955.347 | J89: =J182 -> 2955.347 | K89: =K182 -> 2955.347 | L89: =L182 -> 2955.347
B90: Equity-accounted investments | D90: =Hist!D45 -> 0 | E90: =Hist!E45 -> 75.696 | F90: =Hist!F45 -> 190.58 | G90: =Hist!G45 -> 188.721 | H90: =G90+H65-Hist!E395 -> 413.542 | I90: =H90+I65 -> 413.542 | J90: =I90+J65 -> 413.542 | K90: =J90+K65 -> 413.542 | L90: =K90+L65 -> 413.542
B91: Other non-current assets | D91: =SUM(Hist!D46:D48) -> 164.792 | E91: =SUM(Hist!E46:E48) -> 119.176 | F91: =SUM(Hist!F46:F48) -> 163.767 | G91: =SUM(Hist!G46:G48) -> 223.864 | H91: =G91-H128 -> 335.122 | I91: =H91 -> 335.122 | J91: =I91 -> 335.122 | K91: =J91 -> 335.122 | L91: =K91 -> 335.122
B92: Total non-current assets | D92: =SUM(D88:D91) -> 5088.93 | E92: =SUM(E88:E91) -> 5130.248 | F92: =SUM(F88:F91) -> 7246.172 | G92: =SUM(G88:G91) -> 8476.264 | H92: =SUM(H88:H91) -> 9627.5998 | I92: =SUM(I88:I91) -> 9881.2003 | J92: =SUM(J88:J91) -> 10016.355 | K92: =SUM(K88:K91) -> 10105.451 | L92: =SUM(L88:L91) -> 10151.005
B93: Total assets | D93: =D87+D92 -> 7503.433 | E93: =E87+E92 -> 8027.601 | F93: =F87+F92 -> 10873.015 | G93: =G87+G92 -> 11538.205 | H93: =H87+H92 -> 12663.285 | I93: =I87+I92 -> 13035.494 | J93: =J87+J92 -> 13271.565 | K93: =K87+K92 -> 13454.263 | L93: =L87+L92 -> 13591.034
B95: Liabilities and equity
B96: Trade and other payables | D96: =Hist!D82 -> 1832.832 | E96: =Hist!E82 -> 1982.385 | F96: =Hist!F82 -> 2581.917 | G96: =Hist!G82 -> 2399.429 | H96: =-H166 -> 2451.2892 | I96: =-I166 -> 2584.8685 | J96: =-J166 -> 2686.2293 | K96: =-K166 -> 2780.2444 | L96: =-L166 -> 2871.8638
B97: Other current liabilities | D97: =Hist!D81+Hist!D83 -> 108.212 | E97: =Hist!E81+Hist!E83 -> 263.747 | F97: =Hist!F81+Hist!F83 -> 335.004 | G97: =Hist!G81+Hist!G83 -> 72.668 | H97: =G97 -> 72.668 | I97: =H97 -> 72.668 | J97: =I97 -> 72.668 | K97: =J97 -> 72.668 | L97: =K97 -> 72.668
B98: Bank loans | D98: =Hist!D71+Hist!D79 -> 3550.025 | E98: =Hist!E71+Hist!E79 -> 3601.26 | F98: =Hist!F71+Hist!F79 -> 4769.045 | G98: =Hist!G71+Hist!G79 -> 5577.433 | H98: =H202 -> 6438.024 | I98: =I202 -> 6748.9366 | J98: =J202 -> 6916.491 | K98: =K202 -> 6989.2372 | L98: =L202 -> 6975.2151
B99: Lease liabilities | D99: =Hist!D72+Hist!D80 -> 371.457 | E99: =Hist!E72+Hist!E80 -> 329.543 | F99: =Hist!F72+Hist!F80 -> 414.626 | G99: =Hist!G72+Hist!G80 -> 542.644 | H99: =H209 -> 722.17493 | I99: =I209 -> 702.30826 | J99: =J209 -> 699.00931 | K99: =K209 -> 705.63133 | L99: =L209 -> 718.38022
B100: Other non-current liabilities | D100: =SUM(Hist!D73:D75) -> 353.278 | E100: =SUM(Hist!E73:E75) -> 392.816 | F100: =SUM(Hist!F73:F75) -> 748.415 | G100: =SUM(Hist!G73:G75) -> 663.155 | H100: =G100 -> 663.155 | I100: =H100 -> 663.155 | J100: =I100 -> 663.155 | K100: =J100 -> 663.155 | L100: =K100 -> 663.155
B101: Total liabilities | D101: =SUM(D96:D100) -> 6215.804 | E101: =SUM(E96:E100) -> 6569.751 | F101: =SUM(F96:F100) -> 8849.007 | G101: =SUM(G96:G100) -> 9255.329 | H101: =SUM(H96:H100) -> 10347.311 | I101: =SUM(I96:I100) -> 10771.936 | J101: =SUM(J96:J100) -> 11037.553 | K101: =SUM(K96:K100) -> 11210.936 | L101: =SUM(L96:L100) -> 11301.282
B102: Equity attributable to owners | D102: =SUM(Hist!D60:D65) -> 1332.365 | E102: =SUM(Hist!E60:E65) -> 1457.845 | F102: =SUM(Hist!F60:F65) -> 1690.641 | G102: =SUM(Hist!G60:G65) -> 1947.891 | H102: =G102+H135+H70 -> 1956.9759 | I102: =H102+I135+I70 -> 1884.7798 | J102: =I102+J135+J70 -> 1834.3112 | K102: =J102+K135+K70 -> 1820.7597 | L102: =K102+L135+L70 -> 1842.463
B103: Non-controlling interests | D103: =Hist!D67 -> -44.736 | E103: =Hist!E67 -> 0.005 | F103: =Hist!F67 -> 333.367 | G103: =Hist!G67 -> 334.985 | H103: =G103-H69 -> 358.9981 | I103: =H103-I69 -> 378.77769 | J103: =I103-J69 -> 399.70084 | K103: =J103-K69 -> 422.56699 | L103: =K103-L69 -> 447.28865
B104: Total equity | D104: =D102+D103 -> 1287.629 | E104: =E102+E103 -> 1457.85 | F104: =F102+F103 -> 2024.008 | G104: =G102+G103 -> 2282.876 | H104: =H102+H103 -> 2315.974 | I104: =I102+I103 -> 2263.5575 | J104: =J102+J103 -> 2234.012 | K104: =K102+K103 -> 2243.3267 | L104: =L102+L103 -> 2289.7516
B105: Total liabilities and equity | D105: =D101+D104 -> 7503.433 | E105: =E101+E104 -> 8027.601 | F105: =F101+F104 -> 10873.015 | G105: =G101+G104 -> 11538.205 | H105: =H101+H104 -> 12663.285 | I105: =I101+I104 -> 13035.494 | J105: =J101+J104 -> 13271.565 | K105: =K101+K104 -> 13454.263 | L105: =L101+L104 -> 13591.034
B106: Check: balance (assets less liabilities and equity) | D106: =ROUND(D93-D105,1) -> 0 | E106: =ROUND(E93-E105,1) -> 0 | F106: =ROUND(F93-F105,1) -> 0 | G106: =ROUND(G93-G105,1) -> 0 | H106: =ROUND(H93-H105,1) -> 0 | I106: =ROUND(I93-I105,1) -> 0 | J106: =ROUND(J93-J105,1) -> 0 | K106: =ROUND(K93-K105,1) -> 0 | L106: =ROUND(L93-L105,1) -> 0
B109: Cash flow statement
B110: CZK m | D110: =D$4 -> 2022 | E110: =E$4 -> 2023 | F110: =F$4 -> 2024 | G110: =G$4 -> 2025 | H110: =H$4 -> 2026 | I110: =I$4 -> 2027 | J110: =J$4 -> 2028 | K110: =K$4 -> 2029 | L110: =L$4 -> 2030
B111: Operating activities
B112: Profit before tax | D112: =Hist!D93 -> 399.844 | E112: =Hist!E93 -> 481.942 | F112: =Hist!F93 -> 927.301 | G112: =Hist!G93 -> 932.91 | H112: =H66 -> 649.00271 | I112: =I66 -> 534.58363 | J112: =J66 -> 565.49034 | K112: =K66 -> 618.00407 | L112: =L66 -> 668.15314
...

Sheet Comps
B1: Kofola ČeskoSlovensko | Trading comparables
B2: Peers in their own reporting currency (millions), Kofola in CZK m. Valuation date 30.06.2026.
B4: Peer data at 30.06.2026
B5: Company H1 2026 reports, closing prices on 30.06.2026
D7: Share | E7: Shares | F7: Net | I7: LTM | J7: LTM adj. | K7: LTM net | L7: LTM
B8: Company | C8: Ccy | D8: price | E8: outstanding | F8: debt | G8: NCI | H8: Associates | I8: revenue | J8: EBITDA | K8: profit | L8: ends
D9: per share | E9: m | F9: m | G9: m | H9: m | I9: m | J9: m | K9: m
B10: Coca-Cola HBC | C10: EUR | D10: 57 | E10: 364.03068 | F10: 1413.6 | G10: 96.8 | H10: 0 | I10: 12213.6 | J10: 1942.1 | K10: 1063.1 | L10: Jul-26
B11: A.G. Barr | C11: GBP | D11: 6.33 | E11: 110.84682 | F11: 55.4 | G11: 6.6 | H11: 0 | I11: 456.6 | J11: 79.4 | K11: 49.3 | L11: Aug-26
B12: Royal Unibrew | C12: DKK | D12: 431.4 | E12: 47.827612 | F12: 6610 | G12: 0 | H12: 0 | I12: 15816 | J12: 3040 | K12: 1610 | L12: Jun-26
B13: Olvi | C13: EUR | D13: 32 | E13: 20.635045 | F13: 62.694 | G13: 2.851 | H13: 0.983 | I13: 709.702 | J13: 115.641 | K13: 65.868 | L13: Jun-26
B14: Shown, not in the statistics
B15: Fever-Tree | C15: GBP | D15: 8.125 | E15: 113.11196 | F15: -64.2 | G15: 0 | H15: 0 | I15: 345.8 | J15: 44.1 | K15: 25.2 | L15: Jun-26
B17: Target
B18: Kofola ČeskoSlovensko | C18: CZK | D18: =Inputs!D113 -> 493 | E18: =SharesOut -> 21.333731 | F18: =Hist!E371 -> 6441.73 | G18: =Hist!E351 -> 350.207 | H18: =Hist!E332 -> 390.528 | I18: =Hist!F301 -> 11271.289 | J18: =Hist!F323-Inputs!D127 -> 1774.272 | K18: =Hist!F315+Hist!F322*(1-TaxRate)-Inputs!D127*(1-TaxRate) -> 461.1532 | L18: Jun-26
B20: Trading multiples (LTM)
D22: Market | E22: Enterprise | F22: EV / | G22: EV / | I22: EBITDA | J22: Net debt /
B23: Company | C23: Ccy | D23: cap | E23: value | F23: revenue | G23: EBITDA | H23: P / E | I23: margin | J23: EBITDA
D24: m | E24: m | F24: x | G24: x | H24: x | I24: % | J24: x
B25: Coca-Cola HBC | C25: EUR | D25: =D10*E10 -> 20749.749 | E25: =D25+F10+G10-H10 -> 22260.149 | F25: =E25/I10 -> 1.8225706 | G25: =E25/J10 -> 11.461896 | H25: =D25/K10 -> 19.518153 | I25: =J10/I10 -> 0.15901127 | J25: =F10/J10 -> 0.72787189
B26: A.G. Barr | C26: GBP | D26: =D11*E11 -> 701.66035 | E26: =D26+F11+G11-H11 -> 763.66035 | F26: =E26/I11 -> 1.6724931 | G26: =E26/J11 -> 9.6178885 | H26: =D26/K11 -> 14.232461 | I26: =J11/I11 -> 0.173894 | J26: =F11/J11 -> 0.697733
B27: Royal Unibrew | C27: DKK | D27: =D12*E12 -> 20632.832 | E27: =D27+F12+G12-H12 -> 27242.832 | F27: =E27/I12 -> 1.7224856 | G27: =E27/J12 -> 8.9614578 | H27: =D27/K12 -> 12.815423 | I27: =J12/I12 -> 0.19221042 | J27: =F12/J12 -> 2.1743421
B28: Olvi | C28: EUR | D28: =D13*E13 -> 660.32144 | E28: =D28+F13+G13-H13 -> 724.88344 | F28: =E28/I13 -> 1.0213913 | G28: =E28/J13 -> 6.2683948 | H28: =D28/K13 -> 10.02492 | I28: =J13/I13 -> 0.16294304 | J28: =F13/J13 -> 0.54214336
B29: Average | F29: =AVERAGE(F25:F28) -> 1.5597351 | G29: =AVERAGE(G25:G28) -> 9.0774093 | H29: =AVERAGE(H25:H28) -> 14.14774 | I29: =AVERAGE(I25:I28) -> 0.17201468 | J29: =AVERAGE(J25:J28) -> 1.0355226
B30: Median | F30: =MEDIAN(F25:F28) -> 1.6974893 | G30: =MEDIAN(G25:G28) -> 9.2896732 | H30: =MEDIAN(H25:H28) -> 13.523942 | I30: =MEDIAN(I25:I28) -> 0.16841852 | J30: =MEDIAN(J25:J28) -> 0.71280244
B31: Maximum | F31: =MAX(F25:F28) -> 1.8225706 | G31: =MAX(G25:G28) -> 11.461896 | H31: =MAX(H25:H28) -> 19.518153 | I31: =MAX(I25:I28) -> 0.19221042 | J31: =MAX(J25:J28) -> 2.1743421
B32: Minimum | F32: =MIN(F25:F28) -> 1.0213913 | G32: =MIN(G25:G28) -> 6.2683948 | H32: =MIN(H25:H28) -> 10.02492 | I32: =MIN(I25:I28) -> 0.15901127 | J32: =MIN(J25:J28) -> 0.54214336
B34: Shown, not in the statistics
B35: Fever-Tree | C35: GBP | D35: =D15*E15 -> 919.03464 | E35: =D35+F15+G15-H15 -> 854.83464 | F35: =E35/I15 -> 2.4720493 | G35: =E35/J15 -> 19.384005 | H35: =D35/K15 -> 36.469629 | I35: =J15/I15 -> 0.12753036 | J35: =F15/J15 -> -1.4557823
B37: Target at the 30.06.2026 share price
B38: Kofola ČeskoSlovensko | C38: CZK | D38: =D18*E18 -> 10517.529 | E38: =D38+F18+G18-H18-Model!D295 -> 17366.102 | F38: =E38/I18 -> 1.5407379 | G38: =E38/J18 -> 9.787734 | H38: =D38/K18 -> 22.807018 | I38: =J18/I18 -> 0.15741518 | J38: =F18/J18 -> 3.6306327
B40: Implied value per share from peer multiples
B42: CZK m unless stated | D42: Minimum | E42: Average | F42: Median | G42: Maximum
B43: EV / LTM EBITDA
B44: Peer EV / EBITDA | C44: x | D44: =G32 -> 6.2683948 | E44: =G29 -> 9.0774093 | F44: =G30 -> 9.2896732 | G44: =G31 -> 11.461896
B45: Kofola LTM adjusted EBITDA, bonus-normalised | C45: CZK m | D45: =$J$18 -> 1774.272 | E45: =$J$18 -> 1774.272 | F45: =$J$18 -> 1774.272 | G45: =$J$18 -> 1774.272
B46: Implied enterprise value | C46: CZK m | D46: =D44*D45 -> 11121.837 | E46: =E44*E45 -> 16105.793 | F46: =F44*F45 -> 16482.407 | G46: =G44*G45 -> 20336.522
B47: Less: net debt at 30.06.2026 | C47: CZK m | D47: =Model!$D$292 -> -6441.73 | E47: =Model!$D$292 -> -6441.73 | F47: =Model!$D$292 -> -6441.73 | G47: =Model!$D$292 -> -6441.73
B48: Less: non-controlling interests | C48: CZK m | D48: =Model!$D$293 -> -350.207 | E48: =Model!$D$293 -> -350.207 | F48: =Model!$D$293 -> -350.207 | G48: =Model!$D$293 -> -350.207
B49: Plus: equity-accounted investments | C49: CZK m | D49: =Model!$D$294 -> 390.528 | E49: =Model!$D$294 -> 390.528 | F49: =Model!$D$294 -> 390.528 | G49: =Model!$D$294 -> 390.528
B50: Less: unpaid FY2025 dividend (outside shareholders) | C50: CZK m | D50: =Model!$D$295 -> -447.16405 | E50: =Model!$D$295 -> -447.16405 | F50: =Model!$D$295 -> -447.16405 | G50: =Model!$D$295 -> -447.16405
B51: Implied equity value | C51: CZK m | D51: =SUM(D46:D50) -> 4273.2643 | E51: =SUM(E46:E50) -> 9257.2202 | F51: =SUM(F46:F50) -> 9633.8339 | G51: =SUM(G46:G50) -> 13487.949
B52: Shares outstanding | C52: m | D52: =SharesOut -> 21.333731 | E52: =SharesOut -> 21.333731 | F52: =SharesOut -> 21.333731 | G52: =SharesOut -> 21.333731
B53: Implied value per share | C53: CZK | D53: =D51/D52 -> 200.30553 | E53: =E51/E52 -> 433.92411 | F53: =F51/F52 -> 451.57755 | G53: =G51/G52 -> 632.2358
B54: Upside / (downside) vs share price | C54: % | D54: =D53/Inputs!$D$113-1 -> -0.59370075 | E54: =E53/Inputs!$D$113-1 -> -0.1198294 | F54: =F53/Inputs!$D$113-1 -> -0.084021202 | G54: =G53/Inputs!$D$113-1 -> 0.28242557
B56: P / E
B57: Peer P / E | C57: x | D57: =H32 -> 10.02492 | E57: =H29 -> 14.14774 | F57: =H30 -> 13.523942 | G57: =H31 -> 19.518153 | N57: Peer net profit: CCH comparable, A.G. Barr adjusted, Royal Unibrew and Olvi reported (no one-offs disclosed in the LTM period)
B58: Kofola LTM adjusted net profit to owners, bonus-normalised | C58: CZK m | D58: =$K$18 -> 461.1532 | E58: =$K$18 -> 461.1532 | F58: =$K$18 -> 461.1532 | G58: =$K$18 -> 461.1532
B59: Implied equity value | C59: CZK m | D59: =D57*D58 -> 4623.024 | E59: =E57*E58 -> 6524.2754 | F59: =F57*F58 -> 6236.6093 | G59: =G57*G58 -> 9000.8588
B60: Implied value per share | C60: CZK | D60: =D59/SharesOut -> 216.70021 | E60: =E59/SharesOut -> 305.81971 | F60: =F59/SharesOut -> 292.33561 | G60: =G59/SharesOut -> 421.90739
B61: Upside / (downside) vs share price | C61: % | D61: =D60/Inputs!$D$113-1 -> -0.56044582 | E61: =E60/Inputs!$D$113-1 -> -0.37967605 | F61: =F60/Inputs!$D$113-1 -> -0.40702715 | G61: =G60/Inputs!$D$113-1 -> -0.14420407
B63: Football field data
B65: Implied value per share | D65: Low | E65: Range | F65: High | G65: Median
D66: CZK | E66: CZK | F66: CZK | G66: CZK
B67: Trading comps (EV / EBITDA) | D67: =D53 -> 200.30553 | E67: =F67-D67 -> 431.93028 | F67: =G53 -> 632.2358 | G67: =F53 -> 451.57755
B68: Trading comps (P / E) | D68: =D60 -> 216.70021 | E68: =F68-D68 -> 205.20718 | F68: =G60 -> 421.90739 | G68: =F60 -> 292.33561
B69: Precedent transactions (EV / EBITDA) | D69: =D105 -> 577.18758 | E69: =F69-D69 -> 408.70861 | F69: =G105 -> 985.89619 | G69: =F105 -> 740.66789
B71: Precedent transactions
B72: Acquirers' deal announcements
E74: Stake | F74: EV | H74: EBITDA | I74: EV / | J74: Stated
B75: Target (acquirer) | C75: Ccy | D75: Announced | E75: acquired | F75: (100%) | G75: EBITDA | H75: basis | I75: EBITDA | J75: multiple
E76: % | F76: m | G76: m | I76: x | J76: x
B77: Britvic (Carlsberg) | C77: GBP | D77: 45481 | E77: 1 | F77: 4100 | G77: 303 | H77: LTM Mar-24 | I77: =F77/G77 -> 13.531353 | J77: 13.6
B78: Vrumona (Royal Unibrew) | C78: EUR | D78: 45110 | E78: 1 | F78: 300 | G78: 25 | H78: 2022 norm. | I78: =F78/G78 -> 12 | J78: 12
B79: Hansa Borg (Royal Unibrew) | C79: NOK | D79: 44568 | E79: 0.75 | F79: 3300 | G79: 210 | H79: 2022E norm. | I79: =F79/G79 -> 15.714286 | J79: 16
B80: Coca-Cola Amatil (CCEP) | C80: AUD | D80: 44129 | E80: 1 | F80: 10800 | G80: 1000 | H80: FY19 | I80: =F80/G80 -> 10.8 | J80: 10.9 | N80: EBITDA printed as A$1.0bn (post AASB 16), CCEP announcement 25.10.2020
B81: Average | I81: =AVERAGE(I77:I80) -> 13.01141
B82: Median | I82: =MEDIAN(I77:I80) -> 12.765677
B83: Maximum | I83: =MAX(I77:I80) -> 15.714286
B84: Minimum | I84: =MIN(I77:I80) -> 10.8
B86: Checked but left out: no EV / EBITDA disclosed
B87: Coca-Cola Beverages Africa (Coca-Cola HBC) | C87: USD | D87: 21.10.2025 | E87: 75%
B88: Coca-Cola Bottling Co. of Egypt (Coca-Cola HBC) | C88: USD | D88: 27.08.2021 | E88: 94.7%
B89: Pivovary CZ, now Pivovary Zubr (Kofola) | C89: CZK | D89: 22.11.2023 | E89: 51%
B90: Värska Originaal (Olvi) | C90: EUR | D90: 15.09.2025 | E90: 100%
B91: Fentimans (A.G. Barr) | C91: GBP | D91: 03.02.2026 | E91: 100%
B92: Boost Drinks (A.G. Barr) | C92: GBP | D92: 05.12.2022 | E92: 100%
B94: Kofola: implied value from transaction multiples
B95: CZK m unless stated | D95: Minimum | E95: Average | F95: Median | G95: Maximum
B96: Transaction EV / EBITDA | C96: x | D96: =I84 -> 10.8 | E96: =I81 -> 13.01141 | F96: =I82 -> 12.765677 | G96: =I83 -> 15.714286
B97: Kofola LTM adjusted EBITDA | C97: CZK m | D97: =$J$18 -> 1774.272 | E97: =$J$18 -> 1774.272 | F97: =$J$18 -> 1774.272 | G97: =$J$18 -> 1774.272
B98: Implied enterprise value | C98: CZK m | D98: =D97*D96 -> 19162.138 | E98: =E97*E96 -> 23085.78 | F98: =F97*F96 -> 22649.782 | G98: =G97*G96 -> 27881.417
B99: Less: net debt at 30.06.2026 | C99: CZK m | D99: =Model!$D$292 -> -6441.73 | E99: =Model!$D$292 -> -6441.73 | F99: =Model!$D$292 -> -6441.73 | G99: =Model!$D$292 -> -6441.73
B100: Less: non-controlling interests | C100: CZK m | D100: =Model!$D$293 -> -350.207 | E100: =Model!$D$293 -> -350.207 | F100: =Model!$D$293 -> -350.207 | G100: =Model!$D$293 -> -350.207
B101: Plus: equity-accounted investments | C101: CZK m | D101: =Model!$D$294 -> 390.528 | E101: =Model!$D$294 -> 390.528 | F101: =Model!$D$294 -> 390.528 | G101: =Model!$D$294 -> 390.528
B102: Less: unpaid FY2025 dividend (outside shareholders) | C102: CZK m | D102: =Model!$D$295 -> -447.16405 | E102: =Model!$D$295 -> -447.16405 | F102: =Model!$D$295 -> -447.16405 | G102: =Model!$D$295 -> -447.16405
B103: Implied equity value | C103: CZK m | D103: =SUM(D98:D102) -> 12313.565 | E103: =SUM(E98:E102) -> 16237.207 | F103: =SUM(F98:F102) -> 15801.209 | G103: =SUM(G98:G102) -> 21032.844
B104: Shares outstanding | C104: m | D104: =SharesOut -> 21.333731 | E104: =SharesOut -> 21.333731 | F104: =SharesOut -> 21.333731 | G104: =SharesOut -> 21.333731
B105: Implied value per share | C105: CZK | D105: =D103/D104 -> 577.18758 | E105: =E103/E104 -> 761.10489 | F105: =F103/F104 -> 740.66789 | G105: =G103/G104 -> 985.89619
B106: Upside / (downside) vs share price | C106: % | D106: =D105/Inputs!$D$113-1 -> 0.17076588 | E106: =E105/Inputs!$D$113-1 -> 0.5438233 | F106: =F105/Inputs!$D$113-1 -> 0.50236894 | G106: =G105/Inputs!$D$113-1 -> 0.99978943

Sheet Hist
B1: Kofola ČeskoSlovensko | Historical data
B2: CZK m unless stated
B4: CZK m | D4: 2022 | E4: 2023 | F4: 2024 | G4: 2025 | H4: Source / note
B6: Income statement (as reported)
B7: Revenue | D7: 7875.284 | E7: 8690.103 | F7: 11081.953 | G7: 10754.328 | H7: XBRL (ESEF) primary statements: FY2024-25 from AR2025, FY2023 from AR2024, FY2022 from AR2023
B8: Cost of sales | D8: -4564.018 | E8: -4802.651 | F8: -6037.14 | G8: -5675
B9: Gross profit | D9: 3311.266 | E9: 3887.452 | F9: 5044.813 | G9: 5079.328
B10: Distribution, sales and marketing expenses | D10: -2329.973 | E10: -2487.765 | F10: -3201.001 | G10: -3356.442
B11: Administrative expenses | D11: -466.509 | E11: -707.052 | F11: -705.866 | G11: -606.82
B12: Other operating income | D12: 47.858 | E12: 89.917 | F12: 271.889 | G12: 152.164
B13: Other operating expenses | D13: -80.002 | E13: -35.349 | F13: -166.779 | G13: -103.646
B14: Operating profit (EBIT) | D14: 482.64 | E14: 747.203 | F14: 1243.056 | G14: 1164.584
B15: Finance income | D15: 158.282 | E15: 34.256 | F15: 46.197 | G15: 84.532
B16: Finance costs | D16: -241.078 | E16: -295.532 | F16: -361.47 | G16: -314.448
B17: Share of profit/(loss) of equity-accounted investees | D17: 0 | E17: -3.985 | F17: -0.482 | G17: -1.758
B18: Profit before tax | D18: 399.844 | E18: 481.942 | F18: 927.301 | G18: 932.91
B19: Income tax expense | D19: -135.925 | E19: -112.965 | F19: -274.149 | G19: -251.321
... B22: attributable to non-controlling interests | D22: -5.231 | E22: 3.58 | F22: 55.26 | G22: 7.665
B24: Per share
B25: Basic EPS (CZK) | D25: 12.07 | E25: 16.39 | F25: 26.82 | G25: 30.23 | H25: XBRL (ESEF) primary statements: FY2024-25 from AR2025, FY2023 from AR2024, FY2022 from AR2023
B26: Cash dividend per share paid in the year (CZK) | D26: 11.3 | E26: 13.5 | F26: 21 | G26: 13.5 | H26: AR equity notes
B27: Total dividend per share declared for the fiscal year (CZK) | D27: 13.5 | E27: 13.5 | F27: 21 | G27: 21 | H27: AR equity notes, AGM of 17.06.2026
B28: Shares issued (m) | D28: 22.291948 | E28: 22.291948 | F28: 22.291948 | G28: 22.291948 | H28: H1 2026 report, note 4.14
B29: Treasury shares held by RADENSKA + own shares (m) | D29: 1.062236 | E29: 1.062236 | F29: 1.025266 | G29: 0.998422 | H29: AR2023 / AR2025 equity notes
B30: Shares outstanding, year end (m) | D30: 21.229712 | E30: 21.229712 | F30: 21.266682 | G30: 21.293526
B31: Memo: EBITDA as defined by Kofola
B32: Depreciation and amortisation | D32: 586.096 | E32: 540.421 | F32: 674.076 | G32: 760.644 | H32: Cash flow statement
B33: EBITDA (reported = EBIT + D&A) | D33: 1068.736 | E33: 1287.624 | F33: 1917.132 | G33: 1925.228
B34: One-off items (EBITDA impact) | D34: 41.695 | E34: -34.22 | F34: -66.138 | G34: -108.784 | H34: Segment note, AR capital management note
B35: Adjusted EBITDA | D35: 1110.431 | E35: 1253.404 | F35: 1850.994 | G35: 1816.444
B36: Reported EBIT (source) | D36: 482.64 | E36: 747.203 | F36: 1243.056 | G36: 1164.584 | H36: Segment notes, total column
B37: Reported net profit (source) | D37: 263.919 | E37: 368.977 | F37: 653.152 | G37: 681.589 | H37: Segment notes, total column
B39: Balance sheet (as reported), 31 December
B40: Non-current assets
B41: Property, plant and equipment (incl. right-of-use) | D41: 3098.477 | E41: 3113.262 | F41: 4410.318 | G41: 5267.049 | H41: XBRL (ESEF) primary statements: FY2024-25 from AR2025, FY2023 from AR2024, FY2022 from AR2023
B42: Investment property | E42: 0 | F42: 31.76 | G42: 32.654
B43: Goodwill | D43: 647.969 | E43: 662.318 | F43: 780.942 | G43: 1053.883
B44: Intangible assets | D44: 1177.692 | E44: 1159.796 | F44: 1668.805 | G44: 1710.093
B45: Equity-accounted investments | D45: 0 | E45: 75.696 | F45: 190.58 | G45: 188.721
B46: Other non-current receivables | D46: 164.792 | E46: 80.569 | F46: 109.585 | G46: 135.33
B47: Non-current receivables from related parties | F47: 0 | G47: 58
B48: Deferred tax assets | D48: 0 | E48: 38.607 | F48: 54.182 | G48: 30.534
B49: Total non-current assets | D49: 5088.93 | E49: 5130.248 | F49: 7246.172 | G49: 8476.264
B51: Current assets
B52: Inventories | D52: 766.437 | E52: 706.191 | F52: 941.884 | G52: 1008.021
B53: Trade and other receivables | D53: 997.989 | E53: 1119.938 | F53: 1451.404 | G53: 1338.429
B54: Current tax assets | D54: 23.635 | E54: 0.125 | F54: 3.556 | G54: 80.773
B55: Cash and cash equivalents | D55: 626.442 | E55: 1071.099 | F55: 1229.999 | G55: 634.718
B56: Total current assets | D56: 2414.503 | E56: 2897.353 | F56: 3626.843 | G56: 3061.941
B57: TOTAL ASSETS | D57: 7503.433 | E57: 8027.601 | F57: 10873.015 | G57: 11538.205
B59: Equity
B60: Share capital | D60: 1114.597 | E60: 1114.597 | F60: 1114.597 | G60: 1114.597
B61: Share premium and capital reorganisation reserve | D61: -1962.871 | E61: -1962.871 | F61: -1962.871 | G61: -1962.871
B62: Other reserves | D62: 2516.742 | E62: 2614.776 | F62: 2663.179 | G62: 2574.199
B63: Translation reserve | D63: -30.075 | E63: -1.193 | F63: 15.07 | G63: -20.825
B64: Treasury shares | D64: -467.382 | E64: -467.382 | F64: -451.115 | G64: -439.304
B65: Retained earnings | D65: 161.354 | E65: 159.918 | F65: 311.781 | G65: 682.095
B66: Equity attributable to owners of the parent | D66: 1332.365 | E66: 1457.845 | F66: 1690.641 | G66: 1947.891
B67: Non-controlling interests | D67: -44.736 | E67: 0.005 | F67: 333.367 | G67: 334.985
B68: Total equity | D68: 1287.629 | E68: 1457.85 | F68: 2024.008 | G68: 2282.876
B70: Non-current liabilities
B71: Loans and borrowings (non-current) | D71: 3058.226 | E71: 3153.945 | F71: 3692.064 | G71: 4064.552
B72: Lease liabilities (non-current) | D72: 252.594 | E72: 215.891 | F72: 299.39 | G72: 386.734
B73: Provisions (non-current) | D73: 32.613 | E73: 51.505 | F73: 74.053 | G73: 37.101
B74: Other non-current liabilities | D74: 16.825 | E74: 76.847 | F74: 229.7 | G74: 103.003
B75: Deferred tax liabilities | D75: 303.84 | E75: 264.464 | F75: 444.662 | G75: 523.051
B76: Total non-current liabilities | D76: 3664.098 | E76: 3762.652 | F76: 4739.869 | G76: 5114.441
B78: Current liabilities
B79: Loans and borrowings (current) | D79: 491.799 | E79: 447.315 | F79: 1076.981 | G79: 1512.881
B80: Lease liabilities (current) | D80: 118.863 | E80: 113.652 | F80: 115.236 | G80: 155.91
B81: Provisions (current) | D81: 100.509 | E81: 182.248 | F81: 223.461 | G81: 66.434
B82: Trade and other payables | D82: 1832.832 | E82: 1982.385 | F82: 2581.917 | G82: 2399.429
B83: Current tax liabilities | D83: 7.703 | E83: 81.499 | F83: 111.543 | G83: 6.234
B84: Total current liabilities | D84: 2551.706 | E84: 2807.099 | F84: 4109.138 | G84: 4140.888
B85: Total liabilities | D85: 6215.804 | E85: 6569.751 | F85: 8849.007 | G85: 9255.329
B86: TOTAL EQUITY AND LIABILITIES | D86: 7503.433 | E86: 8027.601 | F86: 10873.015 | G86: 11538.205
B87: Reported total assets (source) | D87: 7503.433 | E87: 8027.601 | F87: 10873.015 | G87: 11538.205
B88: Reported total equity (source) | D88: 1287.629 | E88: 1457.85 | F88: 2024.008 | G88: 2282.876
B90: Cash flow statement (as reported)
B92: Operating activities
B93: Profit before tax | D93: 399.844 | E93: 481.942 | F93: 927.301 | G93: 932.91
B94: Depreciation and amortisation | D94: 586.096 | E94: 540.421 | F94: 674.076 | G94: 760.644
B95: Net interest expense | D95: 209.973 | E95: 242.935 | F95: 294.142 | G95: 254.94
B96: Share of (profit)/loss of equity-accounted investees | D96: 0 | E96: 3.985 | F96: 0.482 | G96: 1.758
B97: Impairment of PP&E / non-current assets | D97: 32.209 | E97: 0 | F97: 9.56 | G97: -7.559
B98: Change in provisions | D98: 7.052 | E98: 98.846 | F98: 56.062 | G98: -193.712
B99: Other impairments (receivables, inventory) | D99: -15.115 | E99: 12.674 | F99: -20.262 | G99: -7.128
B100: Derivatives | D100: -127.841 | E100: -19.752 | F100: -35.495 | G100: 0.753
B101: (Gain)/loss on disposal of non-current assets | D101: -3.085 | E101: -40.502 | F101: -8.181 | G101: -14.492
B102: Unrealised FX (gains)/losses | D102: -16.536 | E102: 23.311 | F102: 32.062 | G102: -85.089
B103: Share-based payments | D103: -1.508 | E103: 158.512 | F103: 81.821 | G103: -82.034
B104: Other non-cash adjustments | D104: -4.995 | E104: 0.702 | F104: -49.629 | G104: -19.683
... B109: Cash flow from operating activities | D109: 922.773 | E109: 1484.65 | F109: 1676.086 | G109: 1216.853
B111: Investing activities
B112: Purchase of PP&E and intangibles (capex) | D112: -413.683 | E112: -417.083 | F112: -824.647 | G112: -1224.456 | H112: XBRL (ESEF) primary statements: FY2024-25 from AR2025, FY2023 from AR2024, FY2022 from AR2023
B113: Proceeds from sale of PP&E | D113: 31.447 | E113: 7.34 | F113: 31.888 | G113: 35.244
B114: Proceeds from sale of Grodzisk Wielkopolski plant | D114: 0 | E114: 119.025
B115: Acquisition of subsidiaries, net of cash acquired | D115: 0 | E115: -22.677 | F115: -1438.403 | G115: -625.726
B116: Investment in equity-accounted investees | D116: 0 | E116: -40.424 | F116: -115 | G116: -1
B117: Capital contribution to JVs and associates | D117: 0 | E117: -38.083
...
